TP2/Multiplicador/Fuentes/multiplicador.vhd
-- TP 2
-- Materia: Sistemas digitales
-- Alumno: Batallan David Leonardo
-- Padron: 97529

library IEEE;
use IEEE.std_logic_1164.all;
use IEEE.numeric_std.all;

entity fp_mul is
    generic(N : natural := 20;
            NE : natural := 6
    );
    port (
        X   : in std_logic_vector(N-1 downto 0); -- Primer operando
        Y   : in std_logic_vector(N-1 downto 0); -- Segundo operando
        Z   : out std_logic_vector(N-1 downto 0) -- Resultado       
    );
end fp_mul;

architecture behavioral of fp_mul is

    -- Constantes auxiliares para manejo de exponentes y formatos
    constant EXC        : natural := 2**(NE-1)-1; -- Valor base del exponente en exceso
    constant NF         : natural := N-NE-1;      -- Cantidad de bits de la mantisa
    constant EXCESO     : unsigned(NE+1 downto 0) := to_unsigned(EXC, NE+2); -- Exceso extendido
    constant E_MIN      : unsigned(NE-1 downto 0) := to_unsigned(0, NE);     -- Exponente mínimo
    constant E_MAX      : unsigned(NE-1 downto 0) := to_unsigned(2**(NE)-2, NE); -- Exponente máximo permitido
    constant E_CEROS    : unsigned(NE+1 downto 0) := to_unsigned(0, NE+2); -- Verificación de exponente nulo
    constant F_CEROS    : unsigned(NF-1 downto 0) := to_unsigned(0, NF);   -- Verificación de mantisa nula
    constant RES_CERO   : unsigned(N-2 downto 0) := to_unsigned(0, N-1);   -- Parte no signo de un resultado cero

    -- Señales internas: separación de campos
    signal sx       : std_logic; -- Bit de signo de X
    signal sy       : std_logic; -- Bit de signo de Y

    signal ex       : unsigned(NE+1 downto 0) := (others => '0'); -- Exponente de X extendido para control de overflow/underflow
    signal ey       : unsigned(NE+1 downto 0) := (others => '0'); -- Exponente de Y extendido
    signal cero_op  : std_logic := '0';                           -- Indicador de si alguno de los operandos es cero

    signal fx       : unsigned(NF-1 downto 0) := (others => '0'); -- Mantisa de X
    signal fy       : unsigned(NF-1 downto 0) := (others => '0'); -- Mantisa de Y

    signal mx       : unsigned(NF downto 0) := (others => '0');   -- Significand de X (1.F)
    signal my       : unsigned(NF downto 0) := (others => '0');   -- Significand de Y (1.F)

    signal sz           : std_logic;                                    -- Signo del resultado
    signal ez           : unsigned(NE-1 downto 0) := (others => '0');   -- Exponente final en exceso
    signal ez_aux       : unsigned(NE+1 downto 0) := (others => '0');   -- Exponente auxiliar intermedio
    signal ez_aux_p     : unsigned(NE+1 downto 0) := (others => '0');   -- Exponente auxiliar ajustado
    signal mz           : unsigned(2*NF+1 downto 0) := (others => '0'); -- Producto de los significands
    signal fz           : unsigned(NF-1 downto 0) := (others => '0');   -- Mantisa resultante
    signal fz_aux       : unsigned(NF-1 downto 0) := (others => '0');   -- Mantisa ajustada (previa al redondeo final)

begin

    -- Separación de campos: signo, exponente y mantisa
    sx <= X(NE+NF);
    sy <= Y(NE+NF);
    ex <= '0' & '0' & unsigned(X(NF+NE-1 downto NF)); -- Agrega ceros al frente para prevenir overflow/underflow
    ey <= '0' & '0' & unsigned(Y(NF+NE-1 downto NF));
    fx <= unsigned(X(NF-1 downto 0));
    fy <= unsigned(Y(NF-1 downto 0));

    -- Detección de operando cero
    cero_op <= '1' when ( (ex = E_CEROS) and (fx = F_CEROS) ) else
               '1' when ( (ey = E_CEROS) and (fy = F_CEROS) ) else
               '0';

    -- Cálculo del signo del resultado
    sz <= sx xor sy;

    -- Construcción de los significands (1.F)
    mx <= '1' & fx;
    my <= '1' & fy;

    -- Producto de los significands
    mz <= mx * my;

    -- Cálculo del nuevo exponente en exceso
    ez_aux <= ex + ey - EXCESO;

    -- Ajuste y redondeo de la mantisa
    fz_aux <=
        mz(2*NF downto NF+1) when mz(2*NF+1) = '1' else
        mz(2*NF-1 downto NF);

    ez_aux_p <= 
        (ez_aux + 1) when mz(2*NF+1) = '1' else ez_aux;

    -- Lógica de saturación del exponente y asignación de mantisa
    ez <= E_MAX when ( (ez_aux_p(NE+1) = '0') and (ez_aux_p(NE) = '1') ) else
          E_MIN when ( (ez_aux_p(NE+1) = '1') and (ez_aux_p(NE) = '1') ) else
          ez_aux_p(NE-1 downto 0);

    fz <= (others => '1') when ( (ez_aux_p(NE+1) = '0') and (ez_aux_p(NE) = '1') ) else
          (others => '0') when ( (ez_aux_p(NE+1) = '1') and (ez_aux_p(NE) = '1') ) else
          fz_aux;

    -- Resultado final: cero si corresponde, o número normalizado
    Z <= std_logic_vector(sz & RES_CERO) when (cero_op = '1') else 
         std_logic_vector(sz & ez & fz);

end architecture behavioral;

TP2/Multiplicador/Fuentes/tb_multiplicador.vhd
-- TP 2
-- Materia: Sistemas digitales
-- Alumno: Batallan David Leonardo
-- Padron: 97529

library IEEE;
use IEEE.std_logic_1164.all;
use IEEE.numeric_std.all;
use std.textio.all;

entity tb_fpmul is
end entity tb_fpmul;

architecture tb_arch of tb_fpmul is

    constant FILE_PATH  : string := "../../Archivos_de_Prueba/fmul_21_7.txt";
    constant TCK        : time := 20 ns; -- Ciclo de reloj
    constant F_SIZE     : natural := 21; -- Bits de la mantisa
    constant EXP_SIZE   : natural := 7;  -- Bits del exponente
    constant WORD_SIZE  : natural := EXP_SIZE + F_SIZE + 1; -- Total de bits (incluye bit de signo)

    signal clk      : std_logic := '0';
    signal x_file   : std_logic_vector(WORD_SIZE-1 downto 0) := (others => '0');
    signal y_file   : std_logic_vector(WORD_SIZE-1 downto 0) := (others => '0');
    signal z_file   : std_logic_vector(WORD_SIZE-1 downto 0) := (others => '0');
    signal z_dut    : std_logic_vector(WORD_SIZE-1 downto 0) := (others => '0');

    signal ciclos   : integer := 0;
    signal errores  : integer := 0;

    file datos : text open read_mode is FILE_PATH;
    
begin

    clk <= not(clk) after TCK/2; -- Generador de reloj

    Test_Sequence: process 
        variable l   : line;
        variable ch  : character := ' ';
        variable aux : integer;
    begin
        while not(endfile(datos)) loop
            wait until rising_edge(clk);
            -- Incremento de contador de ciclos (uso opcional para depuración)
            ciclos <= ciclos + 1;
            -- Lectura de una línea del archivo de pruebas
            readline(datos, l);
            -- Lectura del primer operando (X) desde la línea
            read(l, aux);
            x_file <= std_logic_vector(to_unsigned(aux, WORD_SIZE));
            -- Lectura del carácter separador
            read(l, ch);
            -- Lectura del segundo operando (Y)
            read(l, aux);
            y_file <= std_logic_vector(to_unsigned(aux, WORD_SIZE));
            -- Lectura del siguiente separador
            read(l, ch);
            -- Lectura del valor esperado de salida (Z)
            read(l, aux);
            z_file <= std_logic_vector(to_unsigned(aux, WORD_SIZE));
        end loop;

        file_close(datos); -- Cierre del archivo de entrada

        -- Finalización explícita de la simulación
        assert false report
            "Fin de la simulacion" severity failure;

    end process Test_Sequence;

    -- Instancia del módulo a probar (DUT)
    DUT: entity work.fp_mul(behavioral)
    generic map(
        N => WORD_SIZE,
        NE => EXP_SIZE
    )
    port map(
        X => x_file,
        Y => y_file,
        Z => z_dut
    );

    -- Proceso de verificación: compara la salida del DUT con la referencia
    verificacion: process(clk)
    begin
        if rising_edge(clk) then
            assert to_integer(unsigned(z_file)) = to_integer(unsigned(z_dut)) report
                "Error: Salida del DUT no coincide con referencia (salida del DUT = " &
                integer'image(to_integer(unsigned(z_dut))) &
                ", salida del archivo = " &
                integer'image(to_integer(unsigned(z_file))) & ")"
                severity warning;

            -- Contador de errores si hay discrepancia
            if to_integer(unsigned(z_file)) /= to_integer(unsigned(z_dut)) then
                errores <= errores + 1;
            end if;
        end if;
    end process;

end architecture tb_arch;

TP2/Multiplicador/Simulacion/tb_fpmul.vcd
$date
  Sat Jun 07 00:14:33 2025
$end
$version
  GHDL v0
$end
$timescale
  1 fs
$end
$scope module standard $end
$upscope $end
$scope module std_logic_1164 $end
$upscope $end
$scope module numeric_std $end
$upscope $end
$scope module textio $end
$upscope $end
$scope module tb_fpmul $end
$var reg 1 ! clk $end
$var reg 29 " x_file[28:0] $end
$var reg 29 # y_file[28:0] $end
$var reg 29 $ z_file[28:0] $end
$var reg 29 % z_dut[28:0] $end
$var integer 32 & ciclos $end
$var integer 32 ' errores $end
$scope module dut $end
$var reg 29 ( x[28:0] $end
$var reg 29 ) y[28:0] $end
$var reg 29 * z[28:0] $end
$var reg 1 + sx $end
$var reg 1 , sy $end
$var reg 9 - ex[8:0] $end
$var reg 9 . ey[8:0] $end
$var reg 1 / cero_op $end
$var reg 21 0 fx[20:0] $end
$var reg 21 1 fy[20:0] $end
$var reg 22 2 mx[21:0] $end
$var reg 22 3 my[21:0] $end
$var reg 1 4 sz $end
$var reg 7 5 ez[6:0] $end
$var reg 9 6 ez_aux[8:0] $end
$var reg 9 7 ez_aux_p[8:0] $end
$var reg 44 8 mz[43:0] $end
$var reg 21 9 fz[20:0] $end
$var reg 21 : fz_aux[20:0] $end
$upscope $end
$upscope $end
$enddefinitions $end
#0
0!
b00000000000000000000000000000 "
b00000000000000000000000000000 #
b00000000000000000000000000000 $
b00000000000000000000000000000 %
b0 &
b0 '
b00000000000000000000000000000 (
b00000000000000000000000000000 )
b00000000000000000000000000000 *
0+
0,
b000000000 -
b000000000 .
1/
b000000000000000000000 0
b000000000000000000000 1
b1000000000000000000000 2
b1000000000000000000000 3
04
b0000000 5
b111000001 6
b111000001 7
b01000000000000000000000000000000000000000000 8
b000000000000000000000 9
b000000000000000000000 :
#10000000
1!
b00000111110110100100000111010 "
b01010001111000011111011100100 #
b00011010101111100110111110111 $
b00011010101111100110111110111 %
b1 &
b00000111110110100100000111010 (
b01010001111000011111011100100 )
b00011010101111100110111110111 *
b000000111 -
b001010001 .
0/
b110110100100000111010 0
b111000011111011100100 1
b1110110100100000111010 2
b1111000011111011100100 3
b0011010 5
b000011001 6
b000011010 7
b11011111001101111101111000100101111110101000 8
b101111100110111110111 9
b101111100110111110111 :
#20000000
0!
#30000000
1!
b00100001111111010111011000000 "
b10111100110010000001100011100 #
b10011111110001011101010111011 $
b10011111110001011101010111011 %
b10 &
b00100001111111010111011000000 (
b10111100110010000001100011100 )
b10011111110001011101010111011 *
1,
b000100001 -
b000111100 .
b111111010111011000000 0
b110010000001100011100 1
b1111111010111011000000 2
b1110010000001100011100 3
14
b0011111 5
b000011110 6
b000011111 7
b11100010111010101110110000110101110100000000 8
b110001011101010111011 9
b110001011101010111011 :
#40000000
0!
#50000000
1!
b11101010011111000001100110010 "
b11100110101010001010010110110 #
b01111110111111111111111111111 $
b01111110111111111111111111111 %
b11 &
b11101010011111000001100110010 (
b11100110101010001010010110110 )
b01111110111111111111111111111 *
1+
b001101010 -
b001100110 .
b011111000001100110010 0
b101010001010010110110 1
b1011111000001100110010 2
b1101010001010010110110 3
04
b1111110 5
b010010001 6
b010010010 7
b10011101101000000001011000010010110110001100 8
b111111111111111111111 9
b001110110100000000101 :
#60000000
0!
#70000000
1!
b01000010010111000110111011010 "
b10111011001011010010010110000 #
b10111110100110011110000101010 $
b10111110100110011110000101010 %
b100 &
b01000010010111000110111011010 (
b10111011001011010010010110000 )
b10111110100110011110000101010 *
0+
b001000010 -
b000111011 .
b010111000110111011010 0
b001011010010010110000 1
b1010111000110111011010 2
b1001011010010010110000 3
14
b0111110 5
b000111110 6
b000111110 7
b01100110011110000101010100110010110111100000 8
b100110011110000101010 9
b100110011110000101010 :
#80000000
0!
#90000000
1!
b11011100101110001010100111100 "
b11110010001001011100011101000 #
b01111110111111111111111111111 $
b01111110111111111111111111111 %
b101 &
b11011100101110001010100111100 (
b11110010001001011100011101000 )
b01111110111111111111111111111 *
1+
b001011100 -
b001110010 .
b101110001010100111100 0
b001001011100011101000 1
b1101110001010100111100 2
b1001001011100011101000 3
04
b1111110 5
b010001111 6
b010001111 7
b01111110011011000101100111100101111001100000 8
b111111111111111111111 9
b111110011011000101100 :
#100000000
0!
#110000000
1!
b00011110101100011101010101100 "
b00001100111010100010011000100 #
b00000000000000000000000000000 $
b00000000000000000000000000000 %
b110 &
b00011110101100011101010101100 (
b00001100111010100010011000100 )
b00000000000000000000000000000 *
0+
0,
b000011110 -
b000001100 .
b101100011101010101100 0
b111010100010011000100 1
b1101100011101010101100 2
b1111010100010011000100 3
b0000000 5
b111101011 6
b111101100 7
b11001111101010001100000101101001101110110000 8
b000000000000000000000 9
b100111110101000110000 :
#120000000
0!
#130000000
1!
b10010100111111110100001110010 "
b00010010111001011111000110100 #
b10000000000000000000000000000 $
b10000000000000000000000000000 %
b111 &
b10010100111111110100001110010 (
b00010010111001011111000110100 )
b10000000000000000000000000000 *
1+
b000010100 -
b000010010 .
b111111110100001110010 0
b111001011111000110100 1
b1111111110100001110010 2
b1111001011111000110100 3
14
b111100111 6
b111101000 7
b11110010100111110110001101111101001100101000 8
b111001010011111011000 :
#140000000
0!
#150000000
1!
b01111000111110010001101011110 "
b00110110110111101101010111010 #
b01110000110110000110001100010 $
b01110000110110000110001100010 %
b1000 &
b01111000111110010001101011110 (
b00110110110111101101010111010 )
b01110000110110000110001100010 *
0+
b001111000 -
b000110110 .
b111110010001101011110 0
b110111101101010111010 1
b1111110010001101011110 2
b1110111101101010111010 3
04
b1110000 5
b001101111 6
b001110000 7
b11101100001100011000101001111011111001001100 8
b110110000110001100010 9
b110110000110001100010 :
#160000000
0!
#170000000
1!
b00110010101101111101001011110 "
b10000100000101101011101111100 #
b10000000000000000000000000000 $
b10000000000000000000000000000 %
b1001 &
b00110010101101111101001011110 (
b10000100000101101011101111100 )
b10000000000000000000000000000 *
1,
b000110010 -
b000000100 .
b101101111101001011110 0
b000101101011101111100 1
b1101101111101001011110 2
b1000101101011101111100 3
14
b0000000 5
b111110111 6
b111110111 7
b01110111101110000111011000100011011110001000 8
b000000000000000000000 9
b110111101110000111011 :
#180000000
0!
#190000000
1!
b10011111101001001110101000010 "
b10110111111001100001001001110 #
b00011000100011111001100101010 $
b00011000100011111001100101010 %
b1010 &
b10011111101001001110101000010 (
b10110111111001100001001001110 )
b00011000100011111001100101010 *
1+
b000011111 -
b000110111 .
b101001001110101000010 0
b111001100001001001110 1
b1101001001110101000010 2
b1111001100001001001110 3
04
b0011000 5
b000010111 6
b000011000 7
b11000111110011001010101010111110111000011100 8
b100011111001100101010 9
b100011111001100101010 :
#200000000
0!
#210000000
1!
b11110100110101110000100000110 "
b00010001000100000110110101110 #
b11000110111101010100001000001 $
b11000110111101010100001000001 %
b1011 &
b11110100110101110000100000110 (
b00010001000100000110110101110 )
b11000110111101010100001000001 *
0,
b001110100 -
b000010001 .
b110101110000100000110 0
b000100000110110101110 1
b1110101110000100000110 2
b1000100000110110101110 3
14
b1000110 5
b001000110 6
b001000110 7
b01111101010100001000001111100100000000010100 8
b111101010100001000001 9
b111101010100001000001 :
#220000000
0!
#230000000
1!
b10100100000100011101000000100 "
b11011011010011011101111100010 #
b01000000011001010001101001001 $
b01000000011001010001101001001 %
b1100 &
b10100100000100011101000000100 (
b11011011010011011101111100010 )
b01000000011001010001101001001 *
1,
b000100100 -
b001011011 .
b000100011101000000100 0
b010011011101111100010 1
b1000100011101000000100 2
b1010011011101111100010 3
04
b1000000 5
b001000000 6
b001000000 7
b01011001010001101001001111000010001110001000 8
b011001010001101001001 9
b011001010001101001001 :
#240000000
0!
#250000000
1!
b01011001000010001101001000000 "
b10011000001110011101101110100 #
b10110010010001001010101111110 $
b10110010010001001010101111110 %
b1101 &
b01011001000010001101001000000 (
b10011000001110011101101110100 )
b10110010010001001010101111110 *
0+
b001011001 -
b000011000 .
b000010001101001000000 0
b001110011101101110100 1
b1000010001101001000000 2
b1001110011101101110100 3
14
b0110010 5
b000110010 6
b000110010 7
b01010001001010101111110011001010010100000000 8
b010001001010101111110 9
b010001001010101111110 :
#260000000
0!
#270000000
1!
b10101101000011011010001110110 "
b01001010111111000000100110100 #
b10111001000010111000110101111 $
b10111001000010111000110101111 %
b1110 &
b10101101000011011010001110110 (
b01001010111111000000100110100 )
b10111001000010111000110101111 *
1+
0,
b000101101 -
b001001010 .
b000011011010001110110 0
b111111000000100110100 1
b1000011011010001110110 2
b1111111000000100110100 3
b0111001 5
b000111000 6
b000111001 7
b10000101110001101011110100100001110111111000 8
b000010111000110101111 9
b000010111000110101111 :
#280000000
0!
#290000000
1!
b10100011011000111110010100000 "
b11001010001111000111011111010 #
b00101110101101111111010100111 $
b00101110101101111111010100111 %
b1111 &
b10100011011000111110010100000 (
b11001010001111000111011111010 )
b00101110101101111111010100111 *
1,
b000100011 -
b011000111110010100000 0
b001111000111011111010 1
b1011000111110010100000 2
b1001111000111011111010 3
04
b0101110 5
b000101110 6
b000101110 7
b01101101111111010100111100100111010001000000 8
b101101111111010100111 9
b101101111111010100111 :
#300000000
0!
#310000000
1!
b00000111000100101011111111110 "
b10100001011001101100101101010 #
b10000000000000000000000000000 $
b10000000000000000000000000000 %
b10000 &
b00000111000100101011111111110 (
b10100001011001101100101101010 )
b10000000000000000000000000000 *
0+
b000000111 -
b000100001 .
b000100101011111111110 0
b011001101100101101010 1
b1000100101011111111110 2
b1011001101100101101010 3
14
b0000000 5
b111101001 6
b111101001 7
b01100000010001001010011101101011110100101100 8
b000000000000000000000 9
b100000010001001010011 :
#320000000
0!
#330000000
1!
b00010010100010101100011100000 "
b01101001101001011001110111110 #
b00111101010001010001011001101 $
b00111101010001010001011001101 %
b10001 &
b00010010100010101100011100000 (
b01101001101001011001110111110 )
b00111101010001010001011001101 *
0,
b000010010 -
b001101001 .
b100010101100011100000 0
b101001011001110111110 1
b1100010101100011100000 2
b1101001011001110111110 3
04
b0111101 5
b000111100 6
b000111101 7
b10100010100010110011010001001001011001000000 8
b010001010001011001101 9
b010001010001011001101 :
#340000000
0!
#350000000
1!
b10100000010011010111010101110 "
b01101100010111000100011100100 #
b11001101110001011010100001001 $
b11001101110001011010100001001 %
b10010 &
b10100000010011010111010101110 (
b01101100010111000100011100100 )
b11001101110001011010100001001 *
1+
b000100000 -
b001101100 .
b010011010111010101110 0
b010111000100011100100 1
b1010011010111010101110 2
b1010111000100011100100 3
14
b1001101 5
b001001101 6
b001001101 7
b01110001011010100001001001100000001011111000 8
b110001011010100001001 9
b110001011010100001001 :
#360000000
0!
#370000000
1!
b01000001001000010001100101100 "
b10110111110010011101101111010 #
b10111010000000101000011101000 $
b10111010000000101000011101000 %
b10011 &
b01000001001000010001100101100 (
b10110111110010011101101111010 )
b10111010000000101000011101000 *
0+
1,
b001000001 -
b000110111 .
b001000010001100101100 0
b110010011101101111010 1
b1001000010001100101100 2
b1110010011101101111010 3
b0111010 5
b000111001 6
b000111010 7
b10000001010000111010000111111110011011111000 8
b000000101000011101000 9
b000000101000011101000 :
#380000000
0!
#390000000
1!
b10001001010111001001010000110 "
b00110100101110001110110110010 #
b10000000000000000000000000000 $
b10000000000000000000000000000 %
b10100 &
b10001001010111001001010000110 (
b00110100101110001110110110010 )
b10000000000000000000000000000 *
1+
0,
b000001001 -
b000110100 .
b010111001001010000110 0
b101110001110110110010 1
b1010111001001010000110 2
b1101110001110110110010 3
b0000000 5
b111111110 6
b111111111 7
b10010110000110001000101011110000111100101100 8
b000000000000000000000 9
b001011000011000100010 :
#400000000
0!
#410000000
1!
b11011101000100111100010110010 "
b11000101011101100010001111100 #
b01100011100100110000100101000 $
b01100011100100110000100101000 %
b10101 &
b11011101000100111100010110010 (
b11000101011101100010001111100 )
b01100011100100110000100101000 *
1,
b001011101 -
b001000101 .
b000100111100010110010 0
b011101100010001111100 1
b1000100111100010110010 2
b1011101100010001111100 3
04
b1100011 5
b001100011 6
b001100011 7
b01100100110000100101000101101011111000111000 8
b100100110000100101000 9
b100100110000100101000 :
#420000000
0!
#430000000
1!
b00010011001101111110101100100 "
b00101010010110001101001101100 #
b00000000000000000000000000000 $
b00000000000000000000000000000 %
b10110 &
b00010011001101111110101100100 (
b00101010010110001101001101100 )
b00000000000000000000000000000 *
0+
0,
b000010011 -
b000101010 .
b001101111110101100100 0
b010110001101001101100 1
b1001101111110101100100 2
b1010110001101001101100 3
b0000000 5
b111111110 6
b111111110 7
b01101001000010010101111110110000111000110000 8
b000000000000000000000 9
b101001000010010101111 :
#440000000
0!
#450000000
1!
b11010010110011011001111001110 "
b11111011010101101011100001000 #
b01111110111111111111111111111 $
b01111110111111111111111111111 %
b10111 &
b11010010110011011001111001110 (
b11111011010101101011100001000 )
b01111110111111111111111111111 *
1+
1,
b001010010 -
b001111011 .
b110011011001111001110 0
b010101101011100001000 1
b1110011011001111001110 2
b1010101101011100001000 3
b1111110 5
b010001110 6
b010001111 7
b10011010011111110111100110111010000001110000 8
b111111111111111111111 9
b001101001111111011110 :
#460000000
0!
#470000000
1!
b01101110100111111111000011110 "
b10101011101101000001101100000 #
b11011011011000100100100100011 $
b11011011011000100100100100011 %
b11000 &
b01101110100111111111000011110 (
b10101011101101000001101100000 )
b11011011011000100100100100011 *
0+
b001101110 -
b000101011 .
b100111111111000011110 0
b101101000001101100000 1
b1100111111111000011110 2
b1101101000001101100000 3
14
b1011011 5
b001011010 6
b001011011 7
b10110001001001001000110111001010010101000000 8
b011000100100100100011 9
b011000100100100100011 :
#480000000
0!
#490000000
1!
b11110000010110111110000101010 "
b01001010001011011011011100100 #
b11111011100110100000000011000 $
b11111011100110100000000011000 %
b11001 &
b11110000010110111110000101010 (
b01001010001011011011011100100 )
b11111011100110100000000011000 *
1+
0,
b001110000 -
b001001010 .
b010110111110000101010 0
b001011011011011100100 1
b1010110111110000101010 2
b1001011011011011100100 3
b1111011 5
b001111011 6
b001111011 7
b01100110100000000011000100100111000101101000 8
b100110100000000011000 9
b100110100000000011000 :
#500000000
0!
#510000000
1!
b11011000010101000001101000000 "
b11010110010010110101100000000 #
b01101111101110000011001010000 $
b01101111101110000011001010000 %
b11010 &
b11011000010101000001101000000 (
b11010110010010110101100000000 )
b01101111101110000011001010000 *
1,
b001011000 -
b001010110 .
b010101000001101000000 0
b010010110101100000000 1
b1010101000001101000000 2
b1010010110101100000000 3
04
b1101111 5
b001101111 6
b001101111 7
b01101110000011001010000110111100000000000000 8
b101110000011001010000 9
b101110000011001010000 :
#520000000
0!
#530000000
1!
b11010100111011101101111001110 "
b00111010110010100011010010000 #
b11010000101110101101111110111 $
b11010000101110101101111110111 %
b11011 &
b11010100111011101101111001110 (
b00111010110010100011010010000 )
b11010000101110101101111110111 *
0,
b001010100 -
b000111010 .
b111011101101111001110 0
b110010100011010010000 1
b1111011101101111001110 2
b1110010100011010010000 3
14
b1010000 5
b001001111 6
b001010000 7
b11011101011011111101110000111111011111100000 8
b101110101101111110111 9
b101110101101111110111 :
#540000000
0!
#550000000
1!
b10011000101011111001110001100 "
b10101100010000001011100000100 #
b00000110000011100101110011110 $
b00000110000011100101110011110 %
b11100 &
b10011000101011111001110001100 (
b10101100010000001011100000100 )
b00000110000011100101110011110 *
1,
b000011000 -
b000101100 .
b101011111001110001100 0
b010000001011100000100 1
b1101011111001110001100 2
b1010000001011100000100 3
04
b0000110 5
b000000101 6
b000000110 7
b10000111001011100111100110010110001000110000 8
b000011100101110011110 9
b000011100101110011110 :
#560000000
0!
#570000000
1!
b11110011000010010100100000000 "
b11100100110101011110000011010 #
b01111110111111111111111111111 $
b01111110111111111111111111111 %
b11101 &
b11110011000010010100100000000 (
b11100100110101011110000011010 )
b01111110111111111111111111111 *
b001110011 -
b001100100 .
b000010010100100000000 0
b110101011110000011010 1
b1000010010100100000000 2
b1110101011110000011010 3
b1111110 5
b010011000 6
b010011000 7
b01111001101110100111011110100010101000000000 8
b111111111111111111111 9
b111001101110100111011 :
#580000000
0!
#590000000
1!
b00110001110001010100000000000 "
b11101111000100110101100111110 #
b11100001111001111000001011111 $
b11100001111001111000001011111 %
b11110 &
b00110001110001010100000000000 (
b11101111000100110101100111110 )
b11100001111001111000001011111 *
0+
b000110001 -
b001101111 .
b110001010100000000000 0
b000100110101100111110 1
b1110001010100000000000 2
b1000100110101100111110 3
14
b1100001 5
b001100001 6
b001100001 7
b01111001111000001011111100001011000000000000 8
b111001111000001011111 9
b111001111000001011111 :
#600000000
0!
#610000000
1!
b10000101100011000011101111100 "
b10110100110011111010010100000 #
b00000000000000000000000000000 $
b00000000000000000000000000000 %
b11111 &
b10000101100011000011101111100 (
b10110100110011111010010100000 )
b00000000000000000000000000000 *
1+
b000000101 -
b000110100 .
b100011000011101111100 0
b110011111010010100000 1
b1100011000011101111100 2
b1110011111010010100000 3
04
b0000000 5
b111111010 6
b111111011 7
b10110011011001111110101100101101110110000000 8
b000000000000000000000 9
b011001101100111111010 :
#620000000
0!
#630000000
1!
b11111110001000000010010101100 "
b10101111100101010001111011100 #
b01101110110001111111110111100 $
b01101110110001111111110111100 %
b100000 &
b11111110001000000010010101100 (
b10101111100101010001111011100 )
b01101110110001111111110111100 *
b001111110 -
b000101111 .
b001000000010010101100 0
b100101010001111011100 1
b1001000000010010101100 2
b1100101010001111011100 3
b1101110 5
b001101110 6
b001101110 7
b01110001111111110111100001011000011111010000 8
b110001111111110111100 9
b110001111111110111100 :
#640000000
0!
#650000000
1!
b00101001001000101100100111000 "
b10010111000101100001110110010 #
b10000001001110111110100010101 $
b10000001001110111110100010101 %
b100001 &
b00101001001000101100100111000 (
b10010111000101100001110110010 )
b10000001001110111110100010101 *
0+
b000101001 -
b000010111 .
b001000101100100111000 0
b000101100001110110010 1
b1001000101100100111000 2
b1000101100001110110010 3
14
b0000001 5
b000000001 6
b000000001 7
b01001110111110100010101010111011000011110000 8
b001110111110100010101 9
b001110111110100010101 :
#660000000
0!
#670000000
1!
b10110011001001110111010010100 "
b00011000110100010110101000100 #
b10001101000011001001001010101 $
b10001101000011001001001010101 %
b100010 &
b10110011001001110111010010100 (
b00011000110100010110101000100 )
b10001101000011001001001010101 *
1+
0,
b000110011 -
b000011000 .
b001001110111010010100 0
b110100010110101000100 1
b1001001110111010010100 2
b1110100010110101000100 3
b0001101 5
b000001100 6
b000001101 7
b10000110010010010101010001110110001101010000 8
b000011001001001010101 9
b000011001001001010101 :
#680000000
0!
#690000000
1!
b01110110111001101101000001010 "
b01010110101011010101010110000 #
b01111110111111111111111111111 $
b01111110111111111111111111111 %
b100011 &
b01110110111001101101000001010 (
b01010110101011010101010110000 )
b01111110111111111111111111111 *
0+
b001110110 -
b001010110 .
b111001101101000001010 0
b101011010101010110000 1
b1111001101101000001010 2
b1101011010101010110000 3
04
b1111110 5
b010001101 6
b010001110 7
b11001100000110110110101100101000101011100000 8
b111111111111111111111 9
b100110000011011011010 :
#700000000
0!
#710000000
1!
b01110100010100111001110011000 "
b01101000010111110101110101010 #
b100100 &
b01110100010100111001110011000 (
b01101000010111110101110101010 )
b001110100 -
b001101000 .
b010100111001110011000 0
b010111110101110101010 1
b1010100111001110011000 2
b1010111110101110101010 3
b010011101 6
b010011101 7
b01110100100001111110110101010100101011110000 8
b110100100001111110110 :
#720000000
0!
#730000000
1!
b11110011111101111011111001100 "
b10110101101001010001001010100 #
b01101010100111100100100001011 $
b01101010100111100100100001011 %
b100101 &
b11110011111101111011111001100 (
b10110101101001010001001010100 )
b01101010100111100100100001011 *
1+
1,
b001110011 -
b000110101 .
b111101111011111001100 0
b101001010001001010100 1
b1111101111011111001100 2
b1101001010001001010100 3
b1101010 5
b001101001 6
b001101010 7
b11001111001001000010111010000110011011110000 8
b100111100100100001011 9
b100111100100100001011 :
#740000000
0!
#750000000
1!
b01110010100011110100101110010 "
b11000101001101011011011011100 #
b11111000111000110001001101110 $
b11111000111000110001001101110 %
b100110 &
b01110010100011110100101110010 (
b11000101001101011011011011100 )
b11111000111000110001001101110 *
0+
b001110010 -
b001000101 .
b100011110100101110010 0
b001101011011011011100 1
b1100011110100101110010 2
b1001101011011011011100 3
14
b1111000 5
b001111000 6
b001111000 7
b01111000110001001101110001111010100111111000 8
b111000110001001101110 9
b111000110001001101110 :
#760000000
0!
#770000000
1!
b10101001111100100011100100000 "
b11100001010001011101101101100 #
b01001100001111010001011010100 $
b01001100001111010001011010100 %
b100111 &
b10101001111100100011100100000 (
b11100001010001011101101101100 )
b01001100001111010001011010100 *
1+
b000101001 -
b001100001 .
b111100100011100100000 0
b010001011101101101100 1
b1111100100011100100000 2
b1010001011101101101100 3
04
b1001100 5
b001001011 6
b001001100 7
b10011110100010110101001110100110000110000000 8
b001111010001011010100 9
b001111010001011010100 :
#780000000
0!
#790000000
1!
b01111011110011111100110100110 "
b10101111011000000110000010000 #
b11101100001111110011010001111 $
b11101100001111110011010001111 %
b101000 &
b01111011110011111100110100110 (
b10101111011000000110000010000 )
b11101100001111110011010001111 *
0+
b001111011 -
b000101111 .
b110011111100110100110 0
b011000000110000010000 1
b1110011111100110100110 2
b1011000000110000010000 3
14
b1101100 5
b001101011 6
b001101100 7
b10011111100110100011110110110110001001100000 8
b001111110011010001111 9
b001111110011010001111 :
#800000000
0!
#810000000
1!
b11001110010110010101100110110 "
b11011010011001110000100001000 #
b01101001111001000101011111100 $
b01101001111001000101011111100 %
b101001 &
b11001110010110010101100110110 (
b11011010011001110000100001000 )
b01101001111001000101011111100 *
1+
b001001110 -
b001011010 .
b010110010101100110110 0
b011001110000100001000 1
b1010110010101100110110 2
b1011001110000100001000 3
04
b1101001 5
b001101001 6
b001101001 7
b01111001000101011111100110111100111110110000 8
b111001000101011111100 9
b111001000101011111100 :
#820000000
0!
#830000000
1!
b10111111011111101010110110000 "
b11011110011101100100110011110 #
b01011111000101111100001000111 $
b01011111000101111100001000111 %
b101010 &
b10111111011111101010110110000 (
b11011110011101100100110011110 )
b01011111000101111100001000111 *
b000111111 -
b001011110 .
b011111101010110110000 0
b011101100100110011110 1
b1011111101010110110000 2
b1011101100100110011110 3
b1011111 5
b001011110 6
b001011111 7
b10001011111000010001111011010001001010100000 8
b000101111100001000111 9
b000101111100001000111 :
#840000000
0!
