TP2/Sumador_Restador/Fuentes/sumador_restador.vhd
-- TP 2
-- Materia: Sistemas digitales
-- Alumno: Batallan David Leonardo
-- Padron: 97529

library IEEE;
use IEEE.std_logic_1164.all;
use IEEE.numeric_std.all;

entity fp_subadd is
    generic(N : natural := 20;
            NE : natural := 6
    );
    port (
        X         : in std_logic_vector(N-1 downto 0); -- Operando de entrada 1 (formato flotante)
        Y         : in std_logic_vector(N-1 downto 0); -- Operando de entrada 2 (formato flotante)
        ctrl      : in std_logic; -- Control de operación: '0' para suma, '1' para resta
        Z         : out std_logic_vector(N-1 downto 0) -- Resultado de la operación (formato flotante)
    );
end fp_subadd;

architecture behavioral of fp_subadd is

    -- Constantes relacionadas al formato
    constant EXC    : natural := 2**(NE-1)-1; -- Valor del sesgo (bias) para el exponente
    constant NF     : natural := N-NE-1; -- Ancho de la mantisa
    constant EXCESO : signed(NE-1 downto 0) := to_signed(EXC, NE);
    constant E_MAX  : signed(NE downto 0) := to_signed(2**(NE)-2, NE+1); -- Máximo valor permitido del exponente
    constant E_MIN  : signed(NE downto 0) := to_signed(0, NE+1);         -- Mínimo valor permitido del exponente

    -- Señales auxiliares
    signal Y_aux    : std_logic_vector(N-1 downto 0) := (others => '0');

    -- Campos de exponente extendidos a NE+1 bits para manejar signos en la resta
    signal ex_aux   : unsigned(NE downto 0) := (others => '0');
    signal ey_aux   : unsigned(NE downto 0) := (others => '0');
    signal resta_E  : unsigned(NE downto 0) := (others => '0'); -- Diferencia entre exponentes

    -- Operandos alineados para la operación
    signal X_p      : unsigned(N-1 downto 0) := (others => '0');
    signal Y_p      : unsigned(N-1 downto 0) := (others => '0');

    -- Campos descompuestos de los operandos
    signal sx_p     : std_logic; -- Bit de signo de X_p
    signal sy_p     : std_logic; -- Bit de signo de Y_p
    signal ex_p     : unsigned(NE-1 downto 0) := (others => '0'); -- Exponente de X_p
    signal ey_p     : unsigned(NE-1 downto 0) := (others => '0'); -- Exponente de Y_p
    signal fx_p     : unsigned(NF-1 downto 0) := (others => '0'); -- Mantisa de X_p
    signal fy_p     : unsigned(NF-1 downto 0) := (others => '0'); -- Mantisa de Y_p
    signal mx_p     : unsigned(NF downto 0) := (others => '0'); -- Significando (mantisa normalizada) de X_p
    signal my_p     : unsigned(NF downto 0) := (others => '0'); -- Significando (mantisa normalizada) de Y_p

    -- Preparación para el alineamiento y suma de los significandos
    -- Se reserva espacio suficiente para manejar el peor caso de desplazamiento entre exponentes
    signal mx_2p    : unsigned(NF+2**(NE)-1 downto 0) := (others => '0');
    signal my_2p    : unsigned(NF+2**(NE)-1 downto 0) := (others => '0');
    signal mx_3p    : unsigned(NF+2**(NE)+1 downto 0) := (others => '0');
    signal my_3p    : unsigned(NF+2**(NE)+1 downto 0) := (others => '0');
    signal mx_4p    : unsigned(NF+2**(NE)+1 downto 0) := (others => '0');
    signal my_4p    : unsigned(NF+2**(NE)+1 downto 0) := (others => '0');

    signal suma     : unsigned(NF+2**(NE)+1 downto 0) := (others => '0'); -- Resultado crudo
    signal suma_p   : unsigned(NF+2**(NE)+1 downto 0) := (others => '0'); -- Resultado positivo (complementado si fue negativo)

    signal fz_aux   : unsigned(NF+2**(NE)+1 downto 0) := (others => '0');
    signal fz_aux_p : unsigned(NF-1 downto 0) := (others => '0');
    signal fz       : unsigned(NF-1 downto 0) := (others => '0');
    signal ez_aux   : signed(NE downto 0) := (others => '0');
    signal ez       : signed(NE-1 downto 0) := (others => '0');
    signal sz       : std_logic := '0'; -- Bit de signo del resultado final
    
    -- Indicadores de si es necesario complementar los operandos
    signal comp_x   : std_logic := '0';
    signal comp_y   : std_logic := '0';
    
    -- Función que retorna la posición del primer '1' más significativo
    function find_one (x0: std_logic_vector) return integer is
        variable found  : boolean;
        variable index  : integer;
    begin
        found := False;

        for i in x0'length-1 downto 0 loop
            if x0(i) = '1' and not found then
                found := True;
                index := i;
            end if;
        end loop;
        
        if index < 0 then
            index := 0;
        end if;

        return index;
    end function;

begin

    -- Negación condicional del operando Y si se desea realizar una resta
    Y_aux <= not(Y(N-1)) & Y(N-2 downto 0) when ctrl = '1' else Y;

    -- Cálculo de exponentes con bit adicional para comparación
    ex_aux <= '0' & unsigned(X(NF+NE-1 downto NF));
    ey_aux <= '0' & unsigned(Y_aux(NF+NE-1 downto NF));
    
    resta_E <= ex_aux - ey_aux;

    -- Determinación del operando con mayor exponente. Se reordenan si es necesario.
    X_p <= unsigned(Y_aux) when resta_E(NE) = '1' else unsigned(X);
    Y_p <= unsigned(X)     when resta_E(NE) = '1' else unsigned(Y_aux);

    -- Extracción de campos
    sx_p <= X_p(NE+NF);
    sy_p <= Y_p(NE+NF);
    ex_p <= X_p(NF+NE-1 downto NF);
    ey_p <= Y_p(NF+NE-1 downto NF);
    fx_p <= X_p(NF-1 downto 0);
    fy_p <= Y_p(NF-1 downto 0);
    mx_p <= '1' & fx_p;
    my_p <= '1' & fy_p;

    -- Determinación de si se requiere complemento a 2
    comp_x <= '1' when sx_p = '1' else '0';
    comp_y <= '1' when sy_p = '1' else '0';

    -- Preparación de significandos para el desplazamiento
    mx_2p(NF downto 0) <= mx_p;
    my_2p(NF downto 0) <= my_p;

    -- Alineación de los significandos de acuerdo a los exponentes
    mx_3p <= '0' & '0' & (mx_2p sll to_integer(ex_p));
    my_3p <= '0' & '0' & (my_2p sll to_integer(ey_p));

    -- Aplicación de complemento si es necesario
    mx_4p <= (not(mx_3p) + 1) when comp_x = '1' else mx_3p;
    my_4p <= (not(my_3p) + 1) when comp_y = '1' else my_3p;

    -- Suma efectiva de los significandos
    suma <= mx_4p + my_4p;

    -- Determinación del signo del resultado final
    sz <= suma(NF+2**(NE)+1);

    -- Aplicación de complemento si el resultado fue negativo
    suma_p <= suma when sz = '0' else (not(suma) + 1);

    -- Normalización del resultado
    fz_aux   <= suma_p sll (suma_p'length - find_one(std_logic_vector(suma_p)));
    fz_aux_p <= fz_aux(fz_aux'length-1 downto fz_aux'length-NF);

    -- Cálculo del nuevo exponente
    ez_aux <= to_signed(find_one(std_logic_vector(suma_p)) - NF, NE+1);

    -- Saturación del exponente y ajuste de la mantisa
    ez <= E_MAX(NE-1 downto 0) when to_integer(ez_aux) > to_integer(E_MAX) else
          E_MIN(NE-1 downto 0) when to_integer(ez_aux) < to_integer(E_MIN) else
          ez_aux(NE-1 downto 0);

    fz <= (others => '1') when to_integer(ez_aux) > to_integer(E_MAX) else
          (others => '0') when to_integer(ez_aux) < to_integer(E_MIN) else
          fz_aux_p;

    -- Construcción del resultado final
    Z <= sz & std_logic_vector(ez) & std_logic_vector(fz);

end architecture behavioral;

TP2/Sumador_Restador/Fuentes/tb_sumador_restador.vhd
-- TP 2
-- Materia: Sistemas digitales
-- Alumno: Batallan David Leonardo
-- Padron: 97529

library IEEE;
use IEEE.std_logic_1164.all;
use IEEE.numeric_std.all;
use std.textio.all;

entity tb_fpsubadd is
end entity tb_fpsubadd;

architecture tb_arch of tb_fpsubadd is

    -- Ruta al archivo de prueba con los casos de test
    constant FILE_PATH  : string := "../../Archivos_de_Prueba/fsub_12_6.txt";

    -- Parámetros de reloj y formato flotante
    constant TCK        : time := 20 ns; -- Período del reloj
    constant F_SIZE     : natural := 12; -- Bits para la mantisa
    constant EXP_SIZE   : natural := 6;  -- Bits para el exponente
    constant WORD_SIZE  : natural := EXP_SIZE + F_SIZE + 1; -- Tamaño total de palabra (signo + exponente + mantisa)

    -- Señales internas
    signal clk      : std_logic := '0';
    signal ctrl_tb  : std_logic := '1'; -- Control para la operación ('1' = resta)

    -- Operandos y resultado esperados desde archivo
    signal x_file   : std_logic_vector(WORD_SIZE-1 downto 0) := (others => '0');
    signal y_file   : std_logic_vector(WORD_SIZE-1 downto 0) := (others => '0');
    signal z_file   : std_logic_vector(WORD_SIZE-1 downto 0) := (others => '0');

    -- Resultado producido por el DUT
    signal z_dut    : std_logic_vector(WORD_SIZE-1 downto 0) := (others => '0');

    -- Contadores de ciclos y errores
    signal ciclos   : integer := 0;
    signal errores  : integer := 0;

    -- Archivo de texto con los vectores de prueba
    file datos : text open read_mode is FILE_PATH;
    
begin

    -- Generador de reloj
    clk <= not(clk) after TCK / 2;

    -- Proceso de lectura y aplicación de vectores de prueba
    Test_Sequence: process 
        variable l   : line;
        variable ch  : character := ' ';
        variable aux : integer;
    begin
        while not(endfile(datos)) loop
            wait until rising_edge(clk);

            -- Incrementa el ciclo (útil para debugging)
            ciclos <= ciclos + 1;

            -- Lee una línea del archivo
            readline(datos, l);

            -- Lee los valores en el orden: X (entero), espacio, Y (entero), espacio, Z esperado (entero)
            read(l, aux);
            x_file <= std_logic_vector(to_unsigned(aux, WORD_SIZE));

            read(l, ch); -- Espacio

            read(l, aux);
            y_file <= std_logic_vector(to_unsigned(aux, WORD_SIZE));

            read(l, ch); -- Espacio

            read(l, aux);
            z_file <= std_logic_vector(to_unsigned(aux, WORD_SIZE));
        end loop;

        file_close(datos); -- Cierre del archivo al finalizar

        -- Finaliza la simulación cuando se termina el archivo
        assert false report
            "Fin de la simulación" severity failure;

    end process Test_Sequence;

    -- Instanciación del DUT (Device Under Test)
    DUT: entity work.fp_subadd(behavioral)
    generic map(
        N  => WORD_SIZE,
        NE => EXP_SIZE
    )
    port map(
        X    => x_file,
        Y    => y_file,
        ctrl => ctrl_tb,
        Z    => z_dut
    );

    -- Proceso de verificación automática
    verificacion: process(clk)
    begin
        if rising_edge(clk) then
            assert to_integer(unsigned(z_file)) = to_integer(unsigned(z_dut)) report
                "Error: la salida del DUT no coincide con el valor esperado. DUT = " &
                integer'image(to_integer(unsigned(z_dut))) &
                ", esperado = " &
                integer'image(to_integer(unsigned(z_file))) & "."
                severity warning;
            
            -- Acumula errores para evaluación posterior
            if to_integer(unsigned(z_file)) /= to_integer(unsigned(z_dut)) then
                errores <= errores + 1;
            end if;
        end if;
    end process;

end architecture tb_arch;

TP2/Sumador_Restador/Simulacion/tb_fpsubadd.vcd
$date
  Fri Jun 06 23:43:38 2025
$end
$version
  GHDL v0
$end
$timescale
  1 fs
$end
$scope module standard $end
$upscope $end
$scope module std_logic_1164 $end
$upscope $end
$scope module numeric_std $end
$upscope $end
$scope module textio $end
$upscope $end
$scope module tb_fpsubadd $end
$var reg 1 ! clk $end
$var reg 1 " ctrl_tb $end
$var reg 19 # x_file[18:0] $end
$var reg 19 $ y_file[18:0] $end
$var reg 19 % z_file[18:0] $end
$var reg 19 & z_dut[18:0] $end
$var integer 32 ' ciclos $end
$var integer 32 ( errores $end
$scope module dut $end
$var reg 19 ) x[18:0] $end
$var reg 19 * y[18:0] $end
$var reg 1 + ctrl $end
$var reg 19 , z[18:0] $end
$var reg 19 - y_aux[18:0] $end
$var reg 7 . ex_aux[6:0] $end
$var reg 7 / ey_aux[6:0] $end
$var reg 7 0 resta_e[6:0] $end
$var reg 19 1 x_p[18:0] $end
$var reg 19 2 y_p[18:0] $end
$var reg 1 3 sx_p $end
$var reg 1 4 sy_p $end
$var reg 6 5 ex_p[5:0] $end
$var reg 6 6 ey_p[5:0] $end
$var reg 12 7 fx_p[11:0] $end
$var reg 12 8 fy_p[11:0] $end
$var reg 13 9 mx_p[12:0] $end
$var reg 13 : my_p[12:0] $end
$var reg 76 ; mx_2p[75:0] $end
$var reg 76 < my_2p[75:0] $end
$var reg 78 = mx_3p[77:0] $end
$var reg 78 > my_3p[77:0] $end
$var reg 78 ? mx_4p[77:0] $end
$var reg 78 @ my_4p[77:0] $end
$var reg 78 A suma[77:0] $end
$var reg 78 B suma_p[77:0] $end
$var reg 78 C fz_aux[77:0] $end
$var reg 12 D fz_aux_p[11:0] $end
$var reg 12 E fz[11:0] $end
$var reg 7 F ez_aux[6:0] $end
$var reg 6 G ez[5:0] $end
$var reg 1 H sz $end
$var reg 1 I comp_x $end
$var reg 1 J comp_y $end
$upscope $end
$upscope $end
$enddefinitions $end
#0
0!
1"
b0000000000000000000 #
b0000000000000000000 $
b0000000000000000000 %
b0000000000000000000 &
b0 '
b0 (
b0000000000000000000 )
b0000000000000000000 *
1+
b0000000000000000000 ,
b1000000000000000000 -
b0000000 .
b0000000 /
b0000000 0
b0000000000000000000 1
b1000000000000000000 2
03
14
b000000 5
b000000 6
b000000000000 7
b000000000000 8
b1000000000000 9
b1000000000000 :
b0000000000000000000000000000000000000000000000000000000000000001000000000000 ;
b0000000000000000000000000000000000000000000000000000000000000001000000000000 <
b000000000000000000000000000000000000000000000000000000000000000001000000000000 =
b000000000000000000000000000000000000000000000000000000000000000001000000000000 >
b000000000000000000000000000000000000000000000000000000000000000001000000000000 ?
b111111111111111111111111111111111111111111111111111111111111111111000000000000 @
b000000000000000000000000000000000000000000000000000000000000000000000000000000 A
b000000000000000000000000000000000000000000000000000000000000000000000000000000 B
b000000000000000000000000000000000000000000000000000000000000000000000000000000 C
b000000000000 D
b000000000000 E
b1110100 F
b000000 G
0H
0I
1J
#10000000
1!
b1101001011101111010 #
b0000100000010001100 $
b1101001011101111010 %
b1101001011101111010 &
b1 '
b1101001011101111010 )
b0000100000010001100 *
b1101001011101111010 ,
b1000100000010001100 -
b0101001 .
b0000100 /
b0100101 0
b1101001011101111010 1
b1000100000010001100 2
13
b101001 5
b000100 6
b011101111010 7
b000010001100 8
b1011101111010 9
b1000010001100 :
b0000000000000000000000000000000000000000000000000000000000000001011101111010 ;
b0000000000000000000000000000000000000000000000000000000000000001000010001100 <
b000000000000000000000000101110111101000000000000000000000000000000000000000000 =
b000000000000000000000000000000000000000000000000000000000000010000100011000000 >
b111111111111111111111111010001000011000000000000000000000000000000000000000000 ?
b111111111111111111111111111111111111111111111111111111111111101111011101000000 @
b111111111111111111111111010001000010111111111111111111111111101111011101000000 A
b000000000000000000000000101110111101000000000000000000000000010000100011000000 B
b011101111010000000000000000000000000100001000110000000000000000000000000000000 C
b011101111010 D
b011101111010 E
b0101001 F
b101001 G
1H
1I
#20000000
0!
#30000000
1!
b1010111010011011000 #
b0000110001000100110 $
b1010111010011011000 %
b1010111010011011000 &
b10 '
b1010111010011011000 )
b0000110001000100110 *
b1010111010011011000 ,
b1000110001000100110 -
b0010111 .
b0000110 /
b0010001 0
b1010111010011011000 1
b1000110001000100110 2
b010111 5
b000110 6
b010011011000 7
b001000100110 8
b1010011011000 9
b1001000100110 :
b0000000000000000000000000000000000000000000000000000000000000001010011011000 ;
b0000000000000000000000000000000000000000000000000000000000000001001000100110 <
b000000000000000000000000000000000000000000101001101100000000000000000000000000 =
b000000000000000000000000000000000000000000000000000000000001001000100110000000 >
b111111111111111111111111111111111111111111010110010100000000000000000000000000 ?
b111111111111111111111111111111111111111111111111111111111110110111011010000000 @
b111111111111111111111111111111111111111111010110010011111110110111011010000000 A
b000000000000000000000000000000000000000000101001101100000001001000100110000000 B
b010011011000000010010001001100000000000000000000000000000000000000000000000000 C
b010011011000 D
b010011011000 E
b0010111 F
b010111 G
#40000000
0!
#50000000
1!
b0111010000100111110 #
b1110101110011100010 $
b0111010001000100101 %
b0111010001000100101 &
b11 '
b0111010000100111110 )
b1110101110011100010 *
b0111010001000100101 ,
b0110101110011100010 -
b0111010 .
b0110101 /
b0000101 0
b0111010000100111110 1
b0110101110011100010 2
03
04
b111010 5
b110101 6
b000100111110 7
b110011100010 8
b1000100111110 9
b1110011100010 :
b0000000000000000000000000000000000000000000000000000000000000001000100111110 ;
b0000000000000000000000000000000000000000000000000000000000000001110011100010 <
b000000010001001111100000000000000000000000000000000000000000000000000000000000 =
b000000000000111001110001000000000000000000000000000000000000000000000000000000 >
b000000010001001111100000000000000000000000000000000000000000000000000000000000 ?
b000000000000111001110001000000000000000000000000000000000000000000000000000000 @
b000000010010001001010001000000000000000000000000000000000000000000000000000000 A
b000000010010001001010001000000000000000000000000000000000000000000000000000000 B
b001000100101000100000000000000000000000000000000000000000000000000000000000000 C
b001000100101 D
b001000100101 E
b0111010 F
b111010 G
0H
0I
0J
#60000000
0!
#70000000
1!
b0000110000000111000 #
b0001101001110001010 $
b1001101001101101001 %
b1001101001101101001 &
b100 '
b0000110000000111000 )
b0001101001110001010 *
b1001101001101101001 ,
b1001101001110001010 -
b0000110 .
b0001101 /
b1111001 0
b1001101001110001010 1
b0000110000000111000 2
13
04
b001101 5
b000110 6
b001110001010 7
b000000111000 8
b1001110001010 9
b1000000111000 :
b0000000000000000000000000000000000000000000000000000000000000001001110001010 ;
b0000000000000000000000000000000000000000000000000000000000000001000000111000 <
b000000000000000000000000000000000000000000000000000010011100010100000000000000 =
b000000000000000000000000000000000000000000000000000000000001000000111000000000 >
b111111111111111111111111111111111111111111111111111101100011101100000000000000 ?
b000000000000000000000000000000000000000000000000000000000001000000111000000000 @
b111111111111111111111111111111111111111111111111111101100100101100111000000000 A
b000000000000000000000000000000000000000000000000000010011011010011001000000000 B
b001101101001100100000000000000000000000000000000000000000000000000000000000000 C
b001101101001 D
b001101101001 E
b0001101 F
b001101 G
1H
1I
0J
#80000000
0!
#90000000
1!
b0111000101101111100 #
b1101100101111100110 $
b0111000101101111101 %
b0111000101101111101 &
b101 '
b0111000101101111100 )
b1101100101111100110 *
b0111000101101111101 ,
b0101100101111100110 -
b0111000 .
b0101100 /
b0001100 0
b0111000101101111100 1
b0101100101111100110 2
03
b111000 5
b101100 6
b101101111100 7
b101111100110 8
b1101101111100 9
b1101111100110 :
b0000000000000000000000000000000000000000000000000000000000000001101101111100 ;
b0000000000000000000000000000000000000000000000000000000000000001101111100110 <
b000000000110110111110000000000000000000000000000000000000000000000000000000000 =
b000000000000000000000110111110011000000000000000000000000000000000000000000000 >
b000000000110110111110000000000000000000000000000000000000000000000000000000000 ?
b000000000000000000000110111110011000000000000000000000000000000000000000000000 @
b000000000110110111110110111110011000000000000000000000000000000000000000000000 A
b000000000110110111110110111110011000000000000000000000000000000000000000000000 B
b101101111101101111100110000000000000000000000000000000000000000000000000000000 C
b101101111101 D
b101101111101 E
b0111000 F
b111000 G
0H
0I
#100000000
0!
#110000000
1!
b0011100011111101000 #
b0101101001000100110 $
b1101101001000100101 %
b1101101001000100101 &
b110 '
b0011100011111101000 )
b0101101001000100110 *
b1101101001000100101 ,
b1101101001000100110 -
b0011100 .
b0101101 /
b1101111 0
b1101101001000100110 1
b0011100011111101000 2
13
04
b101101 5
b011100 6
b001000100110 7
b011111101000 8
b1001000100110 9
b1011111101000 :
b0000000000000000000000000000000000000000000000000000000000000001001000100110 ;
b0000000000000000000000000000000000000000000000000000000000000001011111101000 <
b000000000000000000001001000100110000000000000000000000000000000000000000000000 =
b000000000000000000000000000000000000010111111010000000000000000000000000000000 >
b111111111111111111110110111011010000000000000000000000000000000000000000000000 ?
b000000000000000000000000000000000000010111111010000000000000000000000000000000 @
b111111111111111111110110111011010000010111111010000000000000000000000000000000 A
b000000000000000000001001000100101111101000000110000000000000000000000000000000 B
b001000100101111101000000110000000000000000000000000000000000000000000000000000 C
b001000100101 D
b001000100101 E
b0101101 F
b101101 G
1H
1I
0J
#120000000
0!
#130000000
1!
b0001010101001011110 #
b1111000111100011010 $
b0111000111100011010 %
b0111000111100011010 &
b111 '
b0001010101001011110 )
b1111000111100011010 *
b0111000111100011010 ,
b0111000111100011010 -
b0001010 .
b0111000 /
b1010010 0
b0111000111100011010 1
b0001010101001011110 2
03
b111000 5
b001010 6
b111100011010 7
b101001011110 8
b1111100011010 9
b1101001011110 :
b0000000000000000000000000000000000000000000000000000000000000001111100011010 ;
b0000000000000000000000000000000000000000000000000000000000000001101001011110 <
b000000000111110001101000000000000000000000000000000000000000000000000000000000 =
b000000000000000000000000000000000000000000000000000000011010010111100000000000 >
b000000000111110001101000000000000000000000000000000000000000000000000000000000 ?
b000000000000000000000000000000000000000000000000000000011010010111100000000000 @
b000000000111110001101000000000000000000000000000000000011010010111100000000000 A
b000000000111110001101000000000000000000000000000000000011010010111100000000000 B
b111100011010000000000000000000000000000000000110100101111000000000000000000000 C
b111100011010 D
b111100011010 E
b0111000 F
b111000 G
0H
0I
#140000000
0!
#150000000
1!
b1000110101111101000 #
b0001000111000100010 $
b1001001001010001110 %
b1001001001010001110 &
b1000 '
b1000110101111101000 )
b0001000111000100010 *
b1001001001010001110 ,
b1001000111000100010 -
b0000110 .
b0001000 /
b1111110 0
b1001000111000100010 1
b1000110101111101000 2
13
14
b001000 5
b000110 6
b111000100010 7
b101111101000 8
b1111000100010 9
b1101111101000 :
b0000000000000000000000000000000000000000000000000000000000000001111000100010 ;
b0000000000000000000000000000000000000000000000000000000000000001101111101000 <
b000000000000000000000000000000000000000000000000000000000111100010001000000000 =
b000000000000000000000000000000000000000000000000000000000001101111101000000000 >
b111111111111111111111111111111111111111111111111111111111000011101111000000000 ?
b111111111111111111111111111111111111111111111111111111111110010000011000000000 @
b111111111111111111111111111111111111111111111111111111110110101110010000000000 A
b000000000000000000000000000000000000000000000000000000001001010001110000000000 B
b001010001110000000000000000000000000000000000000000000000000000000000000000000 C
b001010001110 D
b001010001110 E
b0001001 F
b001001 G
1H
1I
1J
#160000000
0!
#170000000
1!
b0101010000101000110 #
b1110110010110010010 $
b0110110010110010011 %
b0110110010110010011 &
b1001 '
b0101010000101000110 )
b1110110010110010010 *
b0110110010110010011 ,
b0110110010110010010 -
b0101010 .
b0110110 /
b1110100 0
b0110110010110010010 1
b0101010000101000110 2
03
04
b110110 5
b101010 6
b010110010010 7
b000101000110 8
b1010110010010 9
b1000101000110 :
b0000000000000000000000000000000000000000000000000000000000000001010110010010 ;
b0000000000000000000000000000000000000000000000000000000000000001000101000110 <
b000000000001010110010010000000000000000000000000000000000000000000000000000000 =
b000000000000000000000001000101000110000000000000000000000000000000000000000000 >
b000000000001010110010010000000000000000000000000000000000000000000000000000000 ?
b000000000000000000000001000101000110000000000000000000000000000000000000000000 @
b000000000001010110010011000101000110000000000000000000000000000000000000000000 A
b000000000001010110010011000101000110000000000000000000000000000000000000000000 B
b010110010011000101000110000000000000000000000000000000000000000000000000000000 C
b010110010011 D
b010110010011 E
b0110110 F
b110110 G
0H
0I
0J
#180000000
0!
#190000000
1!
b1001000110100101000 #
b1001111110010001010 $
b0001111110001001111 %
b0001111110001001111 &
b1010 '
b1001000110100101000 )
b1001111110010001010 *
b0001111110001001111 ,
b0001111110010001010 -
b0001000 .
b0001111 /
b1111001 0
b0001111110010001010 1
b1001000110100101000 2
14
b001111 5
b001000 6
b110010001010 7
b110100101000 8
b1110010001010 9
b1110100101000 :
b0000000000000000000000000000000000000000000000000000000000000001110010001010 ;
b0000000000000000000000000000000000000000000000000000000000000001110100101000 <
b000000000000000000000000000000000000000000000000001110010001010000000000000000 =
b000000000000000000000000000000000000000000000000000000000111010010100000000000 >
b000000000000000000000000000000000000000000000000001110010001010000000000000000 ?
b111111111111111111111111111111111111111111111111111111111000101101100000000000 @
b000000000000000000000000000000000000000000000000001110001001111101100000000000 A
b000000000000000000000000000000000000000000000000001110001001111101100000000000 B
b110001001111101100000000000000000000000000000000000000000000000000000000000000 C
b110001001111 D
b110001001111 E
b0001111 F
b001111 G
1J
#200000000
0!
#210000000
1!
b1010000111001000100 #
b0100110010010100100 $
b1100110010010100100 %
b1100110010010100100 &
b1011 '
b1010000111001000100 )
b0100110010010100100 *
b1100110010010100100 ,
b1100110010010100100 -
b0010000 .
b0100110 /
b1101010 0
b1100110010010100100 1
b1010000111001000100 2
13
b100110 5
b010000 6
b010010100100 7
b111001000100 8
b1010010100100 9
b1111001000100 :
b0000000000000000000000000000000000000000000000000000000000000001010010100100 ;
b0000000000000000000000000000000000000000000000000000000000000001111001000100 <
b000000000000000000000000000101001010010000000000000000000000000000000000000000 =
b000000000000000000000000000000000000000000000000011110010001000000000000000000 >
b111111111111111111111111111010110101110000000000000000000000000000000000000000 ?
b111111111111111111111111111111111111111111111111100001101111000000000000000000 @
b111111111111111111111111111010110101101111111111100001101111000000000000000000 A
b000000000000000000000000000101001010010000000000011110010001000000000000000000 B
b010010100100000000000111100100010000000000000000000000000000000000000000000000 C
b010010100100 D
b010010100100 E
b0100110 F
b100110 G
1H
1I
#220000000
0!
#230000000
1!
b1111001100010011000 #
b0001111100011100000 $
b1111001100010011000 %
b1111001100010011000 &
b1100 '
b1111001100010011000 )
b0001111100011100000 *
b1111001100010011000 ,
b1001111100011100000 -
b0111001 .
b0001111 /
b0101010 0
b1111001100010011000 1
b1001111100011100000 2
b111001 5
b001111 6
b100010011000 7
b100011100000 8
b1100010011000 9
b1100011100000 :
b0000000000000000000000000000000000000000000000000000000000000001100010011000 ;
b0000000000000000000000000000000000000000000000000000000000000001100011100000 <
b000000001100010011000000000000000000000000000000000000000000000000000000000000 =
b000000000000000000000000000000000000000000000000001100011100000000000000000000 >
b111111110011101101000000000000000000000000000000000000000000000000000000000000 ?
b111111111111111111111111111111111111111111111111110011100100000000000000000000 @
b111111110011101100111111111111111111111111111111110011100100000000000000000000 A
b000000001100010011000000000000000000000000000000001100011100000000000000000000 B
b100010011000000000000000000000000000000001100011100000000000000000000000000000 C
b100010011000 D
b100010011000 E
b0111001 F
b111001 G
#240000000
0!
#250000000
1!
b0000011011100110000 #
b1011100100001011000 $
b0011100100001011000 %
b0011100100001011000 &
b1101 '
b0000011011100110000 )
b1011100100001011000 *
b0011100100001011000 ,
b0011100100001011000 -
b0000011 .
b0011100 /
b1100111 0
b0011100100001011000 1
b0000011011100110000 2
03
04
b011100 5
b000011 6
b100001011000 7
b011100110000 8
b1100001011000 9
b1011100110000 :
b0000000000000000000000000000000000000000000000000000000000000001100001011000 ;
b0000000000000000000000000000000000000000000000000000000000000001011100110000 <
b000000000000000000000000000000000000011000010110000000000000000000000000000000 =
b000000000000000000000000000000000000000000000000000000000000001011100110000000 >
b000000000000000000000000000000000000011000010110000000000000000000000000000000 ?
b000000000000000000000000000000000000000000000000000000000000001011100110000000 @
b000000000000000000000000000000000000011000010110000000000000001011100110000000 A
b000000000000000000000000000000000000011000010110000000000000001011100110000000 B
b100001011000000000000000101110011000000000000000000000000000000000000000000000 C
b100001011000 D
b100001011000 E
b0011100 F
b011100 G
0H
0I
0J
#260000000
0!
#270000000
1!
b1100101000010100000 #
b0110000111010101010 $
b1110000111010101100 %
b1110000111010101100 &
b1110 '
b1100101000010100000 )
b0110000111010101010 *
b1110000111010101100 ,
b1110000111010101010 -
b0100101 .
b0110000 /
b1110101 0
b1110000111010101010 1
b1100101000010100000 2
13
14
b110000 5
b100101 6
b111010101010 7
b000010100000 8
b1111010101010 9
b1000010100000 :
b0000000000000000000000000000000000000000000000000000000000000001111010101010 ;
b0000000000000000000000000000000000000000000000000000000000000001000010100000 <
b000000000000000001111010101010000000000000000000000000000000000000000000000000 =
b000000000000000000000000000010000101000000000000000000000000000000000000000000 >
b111111111111111110000101010110000000000000000000000000000000000000000000000000 ?
b111111111111111111111111111101111011000000000000000000000000000000000000000000 @
b111111111111111110000101010011111011000000000000000000000000000000000000000000 A
b000000000000000001111010101100000101000000000000000000000000000000000000000000 B
b111010101100000101000000000000000000000000000000000000000000000000000000000000 C
b111010101100 D
b111010101100 E
b0110000 F
b110000 G
1H
1I
1J
#280000000
0!
#290000000
1!
b1101110010010001100 #
b1011110000011011100 $
b1101110010010001011 %
b1101110010010001011 &
b1111 '
b1101110010010001100 )
b1011110000011011100 *
b1101110010010001011 ,
b0011110000011011100 -
b0101110 .
b0011110 /
b0010000 0
b1101110010010001100 1
b0011110000011011100 2
13
04
b101110 5
b011110 6
b010010001100 7
b000011011100 8
b1010010001100 9
b1000011011100 :
b0000000000000000000000000000000000000000000000000000000000000001010010001100 ;
b0000000000000000000000000000000000000000000000000000000000000001000011011100 <
b000000000000000000010100100011000000000000000000000000000000000000000000000000 =
b000000000000000000000000000000000001000011011100000000000000000000000000000000 >
b111111111111111111101011011101000000000000000000000000000000000000000000000000 ?
b000000000000000000000000000000000001000011011100000000000000000000000000000000 @
b111111111111111111101011011101000001000011011100000000000000000000000000000000 A
b000000000000000000010100100010111110111100100100000000000000000000000000000000 B
b010010001011111011110010010000000000000000000000000000000000000000000000000000 C
b010010001011 D
b010010001011 E
b0101110 F
b101110 G
1I
0J
#300000000
0!
#310000000
1!
b1111001100101010100 #
b0100111111001000010 $
b1111001100101010100 %
b1111001100101010100 &
b10000 '
b1111001100101010100 )
b0100111111001000010 *
b1111001100101010100 ,
b1100111111001000010 -
b0111001 .
b0100111 /
b0010010 0
b1111001100101010100 1
b1100111111001000010 2
14
b111001 5
b100111 6
b100101010100 7
b111001000010 8
b1100101010100 9
b1111001000010 :
b0000000000000000000000000000000000000000000000000000000000000001100101010100 ;
b0000000000000000000000000000000000000000000000000000000000000001111001000010 <
b000000001100101010100000000000000000000000000000000000000000000000000000000000 =
b000000000000000000000000001111001000010000000000000000000000000000000000000000 >
b111111110011010101100000000000000000000000000000000000000000000000000000000000 ?
b111111111111111111111111110000110111110000000000000000000000000000000000000000 @
b111111110011010101011111110000110111110000000000000000000000000000000000000000 A
b000000001100101010100000001111001000010000000000000000000000000000000000000000 B
b100101010100000001111001000010000000000000000000000000000000000000000000000000 C
b100101010100 D
b100101010100 E
b0111001 F
b111001 G
1J
#320000000
0!
