TP1/Fuentes/contadorN.vhd
-- TP 1
-- Materia: Sistemas digitales
-- Alumno: Batallan David Leonardo
-- Padron: 97529

library IEEE;
use IEEE.std_logic_1164.all;
use IEEE.numeric_std.all;

-- Contador generico de N bits con señal del carga
entity counterN is
    generic(
        N : natural := 8
    );
    port(
        rst             : in std_logic;
        clk             : in std_logic;
        load            : in std_logic;
        val             : in std_logic_vector(N-1 downto 0);
        count           : out std_logic_vector(N-1 downto 0);
        seg_30_count    : out std_logic;
        seg_3_count     : out std_logic
    );
end counterN;

architecture behavioral of counterN is

    constant N30_SEG : natural := 1499999999;
    constant N3_SEG : natural := 149999999;
     
    signal  aux_count : unsigned(N-1 downto 0);
    
begin
    
    process(clk,rst)
    begin
        if rst = '1' then
            aux_count <= (others => '0');
        elsif clk = '1' and clk'event then
            if load = '1' then
                aux_count <= unsigned(val);
            else
                aux_count <= aux_count + 1;
            end if;
        end if;
    end process;
    
    count <= std_logic_vector(aux_count);
    
    seg_30_count <= '1' when (aux_count = N30_SEG) else '0';
    
    seg_3_count <= '1' when (aux_count = N3_SEG) else '0';
    

end behavioral;

TP1/Fuentes/mux.vhd
-- TP 1
-- Materia: Sistemas digitales
-- Alumno: Batallan David Leonardo
-- Padron: 97529

library IEEE;
use IEEE.std_logic_1164.all;
use IEEE.numeric_std.all;

entity mux is
    port(
        x0  : in std_logic; -- Entrada 0 mux
        x1  : in std_logic; -- Entrada 1 mux
        s   : in std_logic; -- Selectro mux
        y   : out std_logic -- Salida
    );
end mux;

architecture behavioral of mux is
begin
    process(x0,x1,s)
    begin
        case s is
            when '0' =>
                y <= x0;
            
            when others =>
                y <= x1;
        end case;
    end process;
end behavioral;

TP1/Fuentes/semaforos.vhd
-- TP 1
-- Materia: Sistemas digitales
-- Alumno: Batallan David Leonardo
-- Padrón: 97529

library IEEE;
use IEEE.std_logic_1164.all;
use IEEE.numeric_std.all;

entity semaforos is
	port (
		rst		: in std_logic;
		clk		: in std_logic;
		rojo_1		: out std_logic;
		amarillo_1	: out std_logic;
		verde_1		: out std_logic;
		rojo_2		: out std_logic;
		amarillo_2	: out std_logic;
		verde_2		: out std_logic
	);
end semaforos;

architecture behavioral of semaforos is

	-- Definición de constantes
	constant N_counter	: natural := 31;
	constant OCHO		: unsigned(3 downto 0) := to_unsigned(8, 4);

	-- Definición del tipo de dato "t_state"
	type t_state is (R1_V2, R1A1_V2, V1_A2, V1_R2, A1_R2A2);

	-- Señales
	constant val	: std_logic_vector(N_counter-1 downto 0) := (others => '0');
	signal state	: t_state;
	signal mux_out	: std_logic;
	signal sel_mux	: std_logic;
	signal seg_30	: std_logic;
	signal seg_3	: std_logic;
	signal count	: unsigned(3 downto 0);
	signal d     : unsigned(3 downto 0);

begin

	-- Instancia del MUX
	mux: entity work.mux
		port map (
			x0 => seg_30,
			x1 => seg_3,
			s  => sel_mux,
			y  => mux_out
		);

	-- Instancia del contador
	contador: entity work.counterN
		generic map (N => N_counter)
		port map (
			rst   => rst,
			clk   => clk,
			load  => mux_out,
			val   => val,
			count => open,
			seg_30_count => seg_30,
			seg_3_count  => seg_3
		);

	-- Separación de lógica de incremento
	process(count)
	begin
		if count = OCHO then
			d <= (others => '0');
		else
			d <= count + 1;
		end if;
	end process;


	-- Máquina de estados
	fsm: process(clk, rst)
	begin
		if rst = '1' then
			state <= R1_V2;
			count <= (others => '0');

		elsif rising_edge(clk) then
			case state is

				when R1_V2 =>
					if seg_3 = '1' then
						if count = OCHO then
							state <= R1A1_V2;
							count <= d;
						else
							count <= d;
						end if;
					end if;

				when R1A1_V2 =>
					if seg_3 = '1' then
						state <= V1_A2;
					end if;

				when V1_A2 =>
					if seg_3 = '1' then
						state <= V1_R2;
					end if;

				when V1_R2 =>
					if seg_3 = '1' then
						if count = OCHO then
							state <= A1_R2A2;
							count <= d;
						else
							count <= d;
						end if;
					end if;
				when A1_R2A2 =>
					if seg_3 = '1' then
						state <= R1_V2;
					end if;

			end case;
		end if;
	end process;


	-- Lógica de control del MUX
	sel_mux <= '1' when (	state = R1_V2 or state = R1A1_V2 or
				state = V1_A2 or state = V1_R2 or
				state = A1_R2A2) else '0';

	-- Salidas semáforo 1
	rojo_1	<= '1' 	when 	(state = R1_V2 or state = R1A1_V2) else '0';
	amarillo_1  <= '1' when (state = R1A1_V2 or state = A1_R2A2) else '0';
	verde_1	 <= '1' when 	(state = V1_A2 or state = V1_R2) else '0';

	-- Salidas semáforo 2
	rojo_2	  <= '1' when 	(state = V1_R2 or state = A1_R2A2) else '0';
	amarillo_2  <= '1' when (state = V1_A2 or state = A1_R2A2) else '0';
	verde_2	 <= '1' when 	(state = R1_V2 or state = R1A1_V2) else '0';

end behavioral;

TP1/Fuentes/tb_semaforos.vhd
-- Trabajo Practico Nº1: Implementación de un Sistema Secuencial en VHDL
-- Materia: Sistemas digitales
-- Alumno: Batallan David Leonardo
-- Padron: 97529

library IEEE;
use IEEE.std_logic_1164.all;
use IEEE.numeric_std.all;

entity tb_semaforos is
end tb_semaforos;

architecture behavioral of tb_semaforos is
    
    constant SIM_TIME : time := 200000 ms;
    constant N_TB : natural := 31;

    signal tb_rst           : std_logic;
    signal tb_clk           : std_logic := '0';
    signal tb_rojo_1        : std_logic;
    signal tb_amarillo_1    : std_logic;
    signal tb_verde_1       : std_logic;
    signal tb_rojo_2        : std_logic;
    signal tb_amarillo_2    : std_logic;
    signal tb_verde_2       : std_logic;
    
begin

    tb_rst <= '0', '1' after 1 ns, '0' after 20 ns;
    tb_clk <= not tb_clk after 500 ms; -- Clock con freq : 50 MHz
    
    
    
    I1: entity work.semaforos(behavioral)
    port map(
        rst         => tb_rst,
        clk         => tb_clk,
        rojo_1      => tb_rojo_1,
        amarillo_1  => tb_amarillo_1,
        verde_1     => tb_verde_1,
        rojo_2      => tb_rojo_2,
        amarillo_2  => tb_amarillo_2,
        verde_2     => tb_verde_2
    );
    
end behavioral;

TP1/Simulacion/tb_semaforos.vcd
$date
  Sat May 24 00:02:53 2025
$end
$version
  GHDL v0
$end
$timescale
  1 fs
$end
$scope module standard $end
$upscope $end
$scope module std_logic_1164 $end
$upscope $end
$scope module numeric_std $end
$upscope $end
$scope module tb_semaforos $end
$var reg 1 ! tb_rst $end
$var reg 1 " tb_clk $end
$var reg 1 # tb_rojo_1 $end
$var reg 1 $ tb_amarillo_1 $end
$var reg 1 % tb_verde_1 $end
$var reg 1 & tb_rojo_2 $end
$var reg 1 ' tb_amarillo_2 $end
$var reg 1 ( tb_verde_2 $end
$scope module i1 $end
$var reg 1 ) rst $end
$var reg 1 * clk $end
$var reg 1 + rojo_1 $end
$var reg 1 , amarillo_1 $end
$var reg 1 - verde_1 $end
$var reg 1 . rojo_2 $end
$var reg 1 / amarillo_2 $end
$var reg 1 0 verde_2 $end
$comment state is not handled $end
$var reg 1 1 mux_out $end
$var reg 1 2 sel_mux $end
$var reg 1 3 seg_30 $end
$var reg 1 4 seg_3 $end
$var reg 4 5 count[3:0] $end
$var reg 4 6 d[3:0] $end
$scope module mux $end
$var reg 1 7 x0 $end
$var reg 1 8 x1 $end
$var reg 1 9 s $end
$var reg 1 : y $end
$upscope $end
$scope module contador $end
$var reg 1 ; rst $end
$var reg 1 < clk $end
$var reg 1 = load $end
$var reg 31 > val[30:0] $end
$var reg 31 ? count[30:0] $end
$var reg 1 @ seg_30_count $end
$var reg 1 A seg_3_count $end
$var reg 31 B aux_count[30:0] $end
$upscope $end
$upscope $end
$upscope $end
$enddefinitions $end
#0
0!
0"
1#
0$
0%
0&
0'
1(
0)
0*
1+
0,
0-
0.
0/
10
01
12
03
04
bUUUU 5
bXXXX 6
07
08
19
0:
0;
0<
0=
b0000000000000000000000000000000 >
bUUUUUUUUUUUUUUUUUUUUUUUUUUUUUUU ?
0@
0A
bUUUUUUUUUUUUUUUUUUUUUUUUUUUUUUU B
#1000000
1!
1)
b0000 5
b0001 6
1;
b0000000000000000000000000000000 ?
b0000000000000000000000000000000 B
#20000000
0!
0)
0;
#500000000000000
1"
1*
1<
b0000000000000000000000000000001 ?
b0000000000000000000000000000001 B
#1000000000000000
0"
0*
0<
#1500000000000000
1"
1*
11
14
18
1:
1<
1=
b0000000000000000000000000000010 ?
1A
b0000000000000000000000000000010 B
#2000000000000000
0"
0*
0<
#2500000000000000
1"
1*
01
04
b0001 5
b0010 6
08
0:
1<
0=
b0000000000000000000000000000000 ?
0A
b0000000000000000000000000000000 B
#3000000000000000
0"
0*
0<
#3500000000000000
1"
1*
1<
b0000000000000000000000000000001 ?
b0000000000000000000000000000001 B
#4000000000000000
0"
0*
0<
#4500000000000000
1"
1*
11
14
18
1:
1<
1=
b0000000000000000000000000000010 ?
1A
b0000000000000000000000000000010 B
#5000000000000000
0"
0*
0<
#5500000000000000
1"
1*
01
04
b0010 5
b0011 6
08
0:
1<
0=
b0000000000000000000000000000000 ?
0A
b0000000000000000000000000000000 B
#6000000000000000
0"
0*
0<
#6500000000000000
1"
1*
1<
b0000000000000000000000000000001 ?
b0000000000000000000000000000001 B
#7000000000000000
0"
0*
0<
#7500000000000000
1"
1*
11
14
18
1:
1<
1=
b0000000000000000000000000000010 ?
1A
b0000000000000000000000000000010 B
#8000000000000000
0"
0*
0<
#8500000000000000
1"
1*
01
04
b0011 5
b0100 6
08
0:
1<
0=
b0000000000000000000000000000000 ?
0A
b0000000000000000000000000000000 B
#9000000000000000
0"
0*
0<
#9500000000000000
1"
1*
1<
b0000000000000000000000000000001 ?
b0000000000000000000000000000001 B
#10000000000000000
0"
0*
0<
#10500000000000000
1"
1*
11
14
18
1:
1<
1=
b0000000000000000000000000000010 ?
1A
b0000000000000000000000000000010 B
#11000000000000000
0"
0*
0<
#11500000000000000
1"
1*
01
04
b0100 5
b0101 6
08
0:
1<
0=
b0000000000000000000000000000000 ?
0A
b0000000000000000000000000000000 B
#12000000000000000
0"
0*
0<
#12500000000000000
1"
1*
1<
b0000000000000000000000000000001 ?
b0000000000000000000000000000001 B
#13000000000000000
0"
0*
0<
#13500000000000000
1"
1*
11
14
18
1:
1<
1=
b0000000000000000000000000000010 ?
1A
b0000000000000000000000000000010 B
#14000000000000000
0"
0*
0<
#14500000000000000
1"
1*
01
04
b0101 5
b0110 6
08
0:
1<
0=
b0000000000000000000000000000000 ?
0A
b0000000000000000000000000000000 B
#15000000000000000
0"
0*
0<
#15500000000000000
1"
1*
1<
b0000000000000000000000000000001 ?
b0000000000000000000000000000001 B
#16000000000000000
0"
0*
0<
#16500000000000000
1"
1*
11
14
18
1:
1<
1=
b0000000000000000000000000000010 ?
1A
b0000000000000000000000000000010 B
#17000000000000000
0"
0*
0<
#17500000000000000
1"
1*
01
04
b0110 5
b0111 6
08
0:
1<
0=
b0000000000000000000000000000000 ?
0A
b0000000000000000000000000000000 B
#18000000000000000
0"
0*
0<
#18500000000000000
1"
1*
1<
b0000000000000000000000000000001 ?
b0000000000000000000000000000001 B
#19000000000000000
0"
0*
0<
#19500000000000000
1"
1*
11
14
18
1:
1<
1=
b0000000000000000000000000000010 ?
1A
b0000000000000000000000000000010 B
#20000000000000000
0"
0*
0<
#20500000000000000
1"
1*
01
04
b0111 5
b1000 6
08
0:
1<
0=
b0000000000000000000000000000000 ?
0A
b0000000000000000000000000000000 B
#21000000000000000
0"
0*
0<
#21500000000000000
1"
1*
1<
b0000000000000000000000000000001 ?
b0000000000000000000000000000001 B
#22000000000000000
0"
0*
0<
#22500000000000000
1"
1*
11
14
18
1:
1<
1=
b0000000000000000000000000000010 ?
1A
b0000000000000000000000000000010 B
#23000000000000000
0"
0*
0<
#23500000000000000
1"
1*
01
04
b1000 5
b0000 6
08
0:
1<
0=
b0000000000000000000000000000000 ?
0A
b0000000000000000000000000000000 B
#24000000000000000
0"
0*
0<
#24500000000000000
1"
1*
1<
b0000000000000000000000000000001 ?
b0000000000000000000000000000001 B
#25000000000000000
0"
0*
0<
#25500000000000000
1"
1*
11
14
18
1:
1<
1=
b0000000000000000000000000000010 ?
1A
b0000000000000000000000000000010 B
#26000000000000000
0"
0*
0<
#26500000000000000
1"
1$
1*
1,
01
04
b0000 5
b0001 6
08
0:
1<
0=
b0000000000000000000000000000000 ?
0A
b0000000000000000000000000000000 B
#27000000000000000
0"
0*
0<
#27500000000000000
1"
1*
1<
b0000000000000000000000000000001 ?
b0000000000000000000000000000001 B
#28000000000000000
0"
0*
0<
#28500000000000000
1"
1*
11
14
18
1:
1<
1=
b0000000000000000000000000000010 ?
1A
b0000000000000000000000000000010 B
#29000000000000000
0"
0*
0<
#29500000000000000
1"
0#
0$
1%
1'
0(
1*
0+
0,
1-
1/
00
01
04
08
0:
1<
0=
b0000000000000000000000000000000 ?
0A
b0000000000000000000000000000000 B
#30000000000000000
0"
0*
0<
#30500000000000000
1"
1*
1<
b0000000000000000000000000000001 ?
b0000000000000000000000000000001 B
#31000000000000000
0"
0*
0<
#31500000000000000
1"
1*
11
14
18
1:
1<
1=
b0000000000000000000000000000010 ?
1A
b0000000000000000000000000000010 B
#32000000000000000
0"
0*
0<
#32500000000000000
1"
1&
0'
1*
1.
0/
01
04
08
0:
1<
0=
b0000000000000000000000000000000 ?
0A
b0000000000000000000000000000000 B
#33000000000000000
0"
0*
0<
#33500000000000000
1"
1*
1<
b0000000000000000000000000000001 ?
b0000000000000000000000000000001 B
#34000000000000000
0"
0*
0<
#34500000000000000
1"
1*
11
14
18
1:
1<
1=
b0000000000000000000000000000010 ?
1A
b0000000000000000000000000000010 B
#35000000000000000
0"
0*
0<
#35500000000000000
1"
1*
01
04
b0001 5
b0010 6
08
0:
1<
0=
b0000000000000000000000000000000 ?
0A
b0000000000000000000000000000000 B
#36000000000000000
0"
0*
0<
#36500000000000000
1"
1*
1<
b0000000000000000000000000000001 ?
b0000000000000000000000000000001 B
#37000000000000000
0"
0*
0<
#37500000000000000
1"
1*
11
14
18
1:
1<
1=
b0000000000000000000000000000010 ?
1A
b0000000000000000000000000000010 B
#38000000000000000
0"
0*
0<
#38500000000000000
1"
1*
01
04
b0010 5
b0011 6
08
0:
1<
0=
b0000000000000000000000000000000 ?
0A
b0000000000000000000000000000000 B
#39000000000000000
0"
0*
0<
#39500000000000000
1"
1*
1<
b0000000000000000000000000000001 ?
b0000000000000000000000000000001 B
#40000000000000000
0"
0*
0<
#40500000000000000
1"
1*
11
14
18
1:
1<
1=
b0000000000000000000000000000010 ?
1A
b0000000000000000000000000000010 B
#41000000000000000
0"
0*
0<
#41500000000000000
1"
1*
01
04
b0011 5
b0100 6
08
0:
1<
0=
b0000000000000000000000000000000 ?
0A
b0000000000000000000000000000000 B
#42000000000000000
0"
0*
0<
#42500000000000000
1"
1*
1<
b0000000000000000000000000000001 ?
b0000000000000000000000000000001 B
#43000000000000000
0"
0*
0<
#43500000000000000
1"
1*
11
14
18
1:
1<
1=
b0000000000000000000000000000010 ?
1A
b0000000000000000000000000000010 B
#44000000000000000
0"
0*
0<
#44500000000000000
1"
1*
01
04
b0100 5
b0101 6
08
0:
1<
0=
b0000000000000000000000000000000 ?
0A
b0000000000000000000000000000000 B
#45000000000000000
0"
0*
0<
#45500000000000000
1"
1*
1<
b0000000000000000000000000000001 ?
b0000000000000000000000000000001 B
#46000000000000000
0"
0*
0<
#46500000000000000
1"
1*
11
14
18
1:
1<
1=
b0000000000000000000000000000010 ?
1A
b0000000000000000000000000000010 B
#47000000000000000
0"
0*
0<
#47500000000000000
1"
1*
01
04
b0101 5
b0110 6
08
0:
1<
0=
b0000000000000000000000000000000 ?
0A
b0000000000000000000000000000000 B
#48000000000000000
0"
0*
0<
#48500000000000000
1"
1*
1<
b0000000000000000000000000000001 ?
b0000000000000000000000000000001 B
#49000000000000000
0"
0*
0<
#49500000000000000
1"
1*
11
14
18
1:
1<
1=
b0000000000000000000000000000010 ?
1A
b0000000000000000000000000000010 B
#50000000000000000
0"
0*
0<
#50500000000000000
1"
1*
01
04
b0110 5
b0111 6
08
0:
1<
0=
b0000000000000000000000000000000 ?
0A
b0000000000000000000000000000000 B
#51000000000000000
0"
0*
0<
#51500000000000000
1"
1*
1<
b0000000000000000000000000000001 ?
b0000000000000000000000000000001 B
#52000000000000000
0"
0*
0<
#52500000000000000
1"
1*
11
14
18
1:
1<
1=
b0000000000000000000000000000010 ?
1A
b0000000000000000000000000000010 B
#53000000000000000
0"
0*
0<
#53500000000000000
1"
1*
01
04
b0111 5
b1000 6
08
0:
1<
0=
b0000000000000000000000000000000 ?
0A
b0000000000000000000000000000000 B
#54000000000000000
0"
0*
0<
#54500000000000000
1"
1*
1<
b0000000000000000000000000000001 ?
b0000000000000000000000000000001 B
#55000000000000000
0"
0*
0<
#55500000000000000
1"
1*
11
14
18
1:
1<
1=
b0000000000000000000000000000010 ?
1A
b0000000000000000000000000000010 B
#56000000000000000
0"
0*
0<
#56500000000000000
1"
1*
01
04
b1000 5
b0000 6
08
0:
1<
0=
b0000000000000000000000000000000 ?
0A
b0000000000000000000000000000000 B
#57000000000000000
0"
0*
0<
#57500000000000000
1"
1*
1<
b0000000000000000000000000000001 ?
b0000000000000000000000000000001 B
#58000000000000000
0"
0*
0<
#58500000000000000
1"
1*
11
14
18
1:
1<
1=
b0000000000000000000000000000010 ?
1A
b0000000000000000000000000000010 B
#59000000000000000
0"
0*
0<
#59500000000000000
1"
1$
0%
1'
1*
1,
0-
1/
01
04
b0000 5
b0001 6
08
0:
1<
0=
b0000000000000000000000000000000 ?
0A
b0000000000000000000000000000000 B
#60000000000000000
0"
0*
0<
#60500000000000000
1"
1*
1<
b0000000000000000000000000000001 ?
b0000000000000000000000000000001 B
#61000000000000000
0"
0*
0<
#61500000000000000
1"
1*
11
14
18
1:
1<
1=
b0000000000000000000000000000010 ?
1A
b0000000000000000000000000000010 B
#62000000000000000
0"
0*
0<
#62500000000000000
1"
1#
0$
0&
0'
1(
1*
1+
0,
0.
0/
10
01
04
08
0:
1<
0=
b0000000000000000000000000000000 ?
0A
b0000000000000000000000000000000 B
#63000000000000000
0"
0*
0<
#63500000000000000
1"
1*
1<
b0000000000000000000000000000001 ?
b0000000000000000000000000000001 B
#64000000000000000
0"
0*
0<
#64500000000000000
1"
1*
11
14
18
1:
1<
1=
b0000000000000000000000000000010 ?
1A
b0000000000000000000000000000010 B
#65000000000000000
0"
0*
0<
#65500000000000000
1"
1*
01
04
b0001 5
b0010 6
08
0:
1<
0=
b0000000000000000000000000000000 ?
0A
b0000000000000000000000000000000 B
#66000000000000000
0"
0*
0<
#66500000000000000
1"
1*
1<
b0000000000000000000000000000001 ?
b0000000000000000000000000000001 B
#67000000000000000
0"
0*
0<
#67500000000000000
1"
1*
11
14
18
1:
1<
1=
b0000000000000000000000000000010 ?
1A
b0000000000000000000000000000010 B
#68000000000000000
0"
0*
0<
#68500000000000000
1"
1*
01
04
b0010 5
b0011 6
08
0:
1<
0=
b0000000000000000000000000000000 ?
0A
b0000000000000000000000000000000 B
#69000000000000000
0"
0*
0<
#69500000000000000
1"
1*
1<
b0000000000000000000000000000001 ?
b0000000000000000000000000000001 B
#70000000000000000
0"
0*
0<
#70500000000000000
1"
1*
11
14
18
1:
1<
1=
b0000000000000000000000000000010 ?
1A
b0000000000000000000000000000010 B
#71000000000000000
0"
0*
0<
#71500000000000000
1"
1*
01
04
b0011 5
b0100 6
08
0:
1<
0=
b0000000000000000000000000000000 ?
0A
b0000000000000000000000000000000 B
#72000000000000000
0"
0*
0<
#72500000000000000
1"
1*
1<
b0000000000000000000000000000001 ?
b0000000000000000000000000000001 B
#73000000000000000
0"
0*
0<
#73500000000000000
1"
1*
11
14
18
1:
1<
1=
b0000000000000000000000000000010 ?
1A
b0000000000000000000000000000010 B
#74000000000000000
0"
0*
0<
#74500000000000000
1"
1*
01
04
b0100 5
b0101 6
08
0:
1<
0=
b0000000000000000000000000000000 ?
0A
b0000000000000000000000000000000 B
#75000000000000000
0"
0*
0<
#75500000000000000
1"
1*
1<
b0000000000000000000000000000001 ?
b0000000000000000000000000000001 B
#76000000000000000
0"
0*
0<
#76500000000000000
1"
1*
11
14
18
1:
1<
1=
b0000000000000000000000000000010 ?
1A
b0000000000000000000000000000010 B
#77000000000000000
0"
0*
0<
#77500000000000000
1"
1*
01
04
b0101 5
b0110 6
08
0:
1<
0=
b0000000000000000000000000000000 ?
0A
b0000000000000000000000000000000 B
#78000000000000000
0"
0*
0<
#78500000000000000
1"
1*
1<
b0000000000000000000000000000001 ?
b0000000000000000000000000000001 B
#79000000000000000
0"
0*
0<
#79500000000000000
1"
1*
11
14
18
1:
1<
1=
b0000000000000000000000000000010 ?
1A
b0000000000000000000000000000010 B
#80000000000000000
0"
0*
0<
#80500000000000000
1"
1*
01
04
b0110 5
b0111 6
08
0:
1<
0=
b0000000000000000000000000000000 ?
0A
b0000000000000000000000000000000 B
#81000000000000000
0"
0*
0<
#81500000000000000
1"
1*
1<
b0000000000000000000000000000001 ?
b0000000000000000000000000000001 B
#82000000000000000
0"
0*
0<
#82500000000000000
1"
1*
11
14
18
1:
1<
1=
b0000000000000000000000000000010 ?
1A
b0000000000000000000000000000010 B
#83000000000000000
0"
0*
0<
#83500000000000000
1"
1*
01
04
b0111 5
b1000 6
08
0:
1<
0=
b0000000000000000000000000000000 ?
0A
b0000000000000000000000000000000 B
#84000000000000000
0"
0*
0<
#84500000000000000
1"
1*
1<
b0000000000000000000000000000001 ?
b0000000000000000000000000000001 B
#85000000000000000
0"
0*
0<
#85500000000000000
1"
1*
11
14
18
1:
1<
1=
b0000000000000000000000000000010 ?
1A
b0000000000000000000000000000010 B
#86000000000000000
0"
0*
0<
#86500000000000000
1"
1*
01
04
b1000 5
b0000 6
08
0:
1<
0=
b0000000000000000000000000000000 ?
0A
b0000000000000000000000000000000 B
#87000000000000000
0"
0*
0<
#87500000000000000
1"
1*
1<
b0000000000000000000000000000001 ?
b0000000000000000000000000000001 B
#88000000000000000
0"
0*
0<
#88500000000000000
1"
1*
11
14
18
1:
1<
1=
b0000000000000000000000000000010 ?
1A
b0000000000000000000000000000010 B
#89000000000000000
0"
0*
0<
#89500000000000000
1"
1$
1*
1,
01
04
b0000 5
b0001 6
08
0:
1<
0=
b0000000000000000000000000000000 ?
0A
b0000000000000000000000000000000 B
#90000000000000000
0"
0*
0<
#90500000000000000
1"
1*
1<
b0000000000000000000000000000001 ?
b0000000000000000000000000000001 B
#91000000000000000
0"
0*
0<
#91500000000000000
1"
1*
11
14
18
1:
1<
1=
b0000000000000000000000000000010 ?
1A
b0000000000000000000000000000010 B
#92000000000000000
0"
0*
0<
#92500000000000000
1"
0#
0$
1%
1'
0(
1*
0+
0,
1-
1/
00
01
04
08
0:
1<
0=
b0000000000000000000000000000000 ?
0A
b0000000000000000000000000000000 B
#93000000000000000
0"
0*
0<
#93500000000000000
1"
1*
1<
b0000000000000000000000000000001 ?
b0000000000000000000000000000001 B
#94000000000000000
0"
0*
0<
#94500000000000000
1"
1*
11
14
18
1:
1<
1=
b0000000000000000000000000000010 ?
1A
b0000000000000000000000000000010 B
#95000000000000000
0"
0*
0<
#95500000000000000
1"
1&
0'
1*
1.
0/
01
04
08
0:
1<
0=
b0000000000000000000000000000000 ?
0A
b0000000000000000000000000000000 B
#96000000000000000
0"
0*
0<
#96500000000000000
1"
1*
1<
b0000000000000000000000000000001 ?
b0000000000000000000000000000001 B
#97000000000000000
0"
0*
0<
#97500000000000000
1"
1*
11
14
18
1:
1<
1=
b0000000000000000000000000000010 ?
1A
b0000000000000000000000000000010 B
#98000000000000000
0"
0*
0<
#98500000000000000
1"
1*
01
04
b0001 5
b0010 6
08
0:
1<
0=
b0000000000000000000000000000000 ?
0A
b0000000000000000000000000000000 B
#99000000000000000
0"
0*
0<
#99500000000000000
1"
1*
1<
b0000000000000000000000000000001 ?
b0000000000000000000000000000001 B
#100000000000000000
0"
0*
0<
#100500000000000000
1"
1*
11
14
18
1:
1<
1=
b0000000000000000000000000000010 ?
1A
b0000000000000000000000000000010 B
#101000000000000000
0"
0*
0<
#101500000000000000
1"
1*
01
04
b0010 5
b0011 6
08
0:
1<
0=
b0000000000000000000000000000000 ?
0A
b0000000000000000000000000000000 B
#102000000000000000
0"
0*
0<
#102500000000000000
1"
1*
1<
b0000000000000000000000000000001 ?
b0000000000000000000000000000001 B
#103000000000000000
0"
0*
0<
#103500000000000000
1"
1*
11
14
18
1:
1<
1=
b0000000000000000000000000000010 ?
1A
b0000000000000000000000000000010 B
#104000000000000000
0"
0*
0<
#104500000000000000
1"
1*
01
04
b0011 5
b0100 6
08
0:
1<
0=
b0000000000000000000000000000000 ?
0A
b0000000000000000000000000000000 B
#105000000000000000
0"
0*
0<
#105500000000000000
1"
1*
1<
b0000000000000000000000000000001 ?
b0000000000000000000000000000001 B
#106000000000000000
0"
0*
0<
#106500000000000000
1"
1*
11
14
18
1:
1<
1=
b0000000000000000000000000000010 ?
1A
b0000000000000000000000000000010 B
#107000000000000000
0"
0*
0<
#107500000000000000
1"
1*
01
04
b0100 5
b0101 6
08
0:
1<
0=
b0000000000000000000000000000000 ?
0A
b0000000000000000000000000000000 B
#108000000000000000
0"
0*
0<
#108500000000000000
1"
1*
1<
b0000000000000000000000000000001 ?
b0000000000000000000000000000001 B
#109000000000000000
0"
0*
0<
#109500000000000000
1"
1*
11
14
18
1:
1<
1=
b0000000000000000000000000000010 ?
1A
b0000000000000000000000000000010 B
#110000000000000000
0"
0*
0<
#110500000000000000
1"
1*
01
04
b0101 5
b0110 6
08
0:
1<
0=
b0000000000000000000000000000000 ?
0A
b0000000000000000000000000000000 B
#111000000000000000
0"
0*
0<
#111500000000000000
1"
1*
1<
b0000000000000000000000000000001 ?
b0000000000000000000000000000001 B
#112000000000000000
0"
0*
0<
#112500000000000000
1"
1*
11
14
18
1:
1<
1=
b0000000000000000000000000000010 ?
1A
b0000000000000000000000000000010 B
#113000000000000000
0"
0*
0<
#113500000000000000
1"
1*
01
04
b0110 5
b0111 6
08
0:
1<
0=
b0000000000000000000000000000000 ?
0A
b0000000000000000000000000000000 B
#114000000000000000
0"
0*
0<
#114500000000000000
1"
1*
1<
b0000000000000000000000000000001 ?
b0000000000000000000000000000001 B
#115000000000000000
0"
0*
0<
#115500000000000000
1"
1*
11
14
18
1:
1<
1=
b0000000000000000000000000000010 ?
1A
b0000000000000000000000000000010 B
#116000000000000000
0"
0*
0<
#116500000000000000
1"
1*
01
04
b0111 5
b1000 6
08
0:
1<
0=
b0000000000000000000000000000000 ?
0A
b0000000000000000000000000000000 B
#117000000000000000
0"
0*
0<
#117500000000000000
1"
1*
1<
b0000000000000000000000000000001 ?
b0000000000000000000000000000001 B
#118000000000000000
0"
0*
0<
#118500000000000000
1"
1*
11
14
18
1:
1<
1=
b0000000000000000000000000000010 ?
1A
b0000000000000000000000000000010 B
#119000000000000000
0"
0*
0<
#119500000000000000
1"
1*
01
04
b1000 5
b0000 6
08
0:
1<
0=
b0000000000000000000000000000000 ?
0A
b0000000000000000000000000000000 B
#120000000000000000
0"
0*
0<
#120500000000000000
1"
1*
1<
b0000000000000000000000000000001 ?
b0000000000000000000000000000001 B
#121000000000000000
0"
0*
0<
#121500000000000000
1"
1*
11
14
18
1:
1<
1=
b0000000000000000000000000000010 ?
1A
b0000000000000000000000000000010 B
#122000000000000000
0"
0*
0<
#122500000000000000
1"
1$
0%
1'
1*
1,
0-
1/
01
04
b0000 5
b0001 6
08
0:
1<
0=
b0000000000000000000000000000000 ?
0A
b0000000000000000000000000000000 B
#123000000000000000
0"
0*
0<
#123500000000000000
1"
1*
1<
b0000000000000000000000000000001 ?
b0000000000000000000000000000001 B
#124000000000000000
0"
0*
0<
#124500000000000000
1"
1*
11
14
18
1:
1<
1=
b0000000000000000000000000000010 ?
1A
b0000000000000000000000000000010 B
#125000000000000000
0"
0*
0<
#125500000000000000
1"
1#
0$
0&
0'
1(
1*
1+
0,
0.
0/
10
01
04
08
0:
1<
0=
b0000000000000000000000000000000 ?
0A
b0000000000000000000000000000000 B
#126000000000000000
0"
0*
0<
#126500000000000000
1"
1*
1<
b0000000000000000000000000000001 ?
b0000000000000000000000000000001 B
#127000000000000000
0"
0*
0<
#127500000000000000
1"
1*
11
14
18
1:
1<
1=
b0000000000000000000000000000010 ?
1A
b0000000000000000000000000000010 B
#128000000000000000
0"
0*
0<
#128500000000000000
1"
1*
01
04
b0001 5
b0010 6
08
0:
1<
0=
b0000000000000000000000000000000 ?
0A
b0000000000000000000000000000000 B
#129000000000000000
0"
0*
0<
#129500000000000000
1"
1*
1<
b0000000000000000000000000000001 ?
b0000000000000000000000000000001 B
#130000000000000000
0"
0*
0<
#130500000000000000
1"
1*
11
14
18
1:
1<
1=
b0000000000000000000000000000010 ?
1A
b0000000000000000000000000000010 B
#131000000000000000
0"
0*
0<
#131500000000000000
1"
1*
01
04
b0010 5
b0011 6
08
0:
1<
0=
b0000000000000000000000000000000 ?
0A
b0000000000000000000000000000000 B
#132000000000000000
0"
0*
0<
#132500000000000000
1"
1*
1<
b0000000000000000000000000000001 ?
b0000000000000000000000000000001 B
#133000000000000000
0"
0*
0<
#133500000000000000
1"
1*
11
14
18
1:
1<
1=
b0000000000000000000000000000010 ?
1A
b0000000000000000000000000000010 B
#134000000000000000
0"
0*
0<
#134500000000000000
1"
1*
01
04
b0011 5
b0100 6
08
0:
1<
0=
b0000000000000000000000000000000 ?
0A
b0000000000000000000000000000000 B
#135000000000000000
0"
0*
0<
#135500000000000000
1"
1*
1<
b0000000000000000000000000000001 ?
b0000000000000000000000000000001 B
#136000000000000000
0"
0*
0<
#136500000000000000
1"
1*
11
14
18
1:
1<
1=
b0000000000000000000000000000010 ?
1A
b0000000000000000000000000000010 B
#137000000000000000
0"
0*
0<
